Workbook

Sheet README
A1: TransferIQ synthetic data set (v2: Northeastern + NYU)
A2: Purpose | B2: Test data for the EvoHack 2026 transfer credit evaluation prototype (Boston University problem statement).
A3: Status | B3: TEST DATA. Students, grades, transcripts, syllabus content, instructors and decisions are invented. Transcripts and syllabi were NOT issued by Northeastern or NYU.
A4: Source schools | B4: Northeastern University (NEU) and New York University (NYU), as given in the hackathon workbook. Two fictional helper schools cover cases NU/NYU cannot: Pinecrest State College (quarter calendar, 1 course) and Summit Online Institute (not regionally accredited, 2 courses).
A5: BU courses | B5: 150 courses across 5 majors. 41 codes/titles come from the provided BU workbook; 109 are synthetic. All descriptions, topics and outcomes are synthetic.
A6: External courses | B6: 194 courses: 76 real NU/NYU catalog courses (code, title, credits from the workbook; content synthetic) + 115 synthetic NU/NYU-style courses + 3 helper-school courses. See the Source column.
A7: Ground truth | B7: Columns with a dark red header (gt_*) are answer keys. For the 76 real courses the counterpart follows the workbook's Course Match sheet. Hide gt_* from the AI matcher.
A8: Past decisions | B8: 100 decisions = the stand-in equivalency table. split = train (reusable, 70) or holdout (hidden from the app, used to measure AI accuracy, 30).
A9: Transcripts | B9: 4 students, 7 transcript PDFs, 56 course lines. Transcript Lines shows the expected rules-engine outcome for each line.
A10: Syllabi | B10: 12 syllabus PDFs: demo maybe-courses, one incomplete (TM), one with a prompt-injection line (red team), three for held-out courses.
A11: Codes (assumption) | B11: Elective codes follow the sponsor's 'ends in TR' rule: CAS <DEPT> 1TR (100-level) / 2TR (200+), TFRGEN 1TR for general electives. No credit = TFRGEN NOCRDT, 0 units, TX.
A12: Formulas | B12: Transcript Lines 'Units if approved' and the Students summary columns are live formulas.
A13: Seed files | B13: seed/*.csv (one per sheet; list fields joined with ' | ') and seed/transferiq_seed.json (lists kept as arrays).

Sheet Demo Scenario
A1: Step | B1: Stage | C1: Action / input | D1: Expected result
A2: 1 | B2: Upload | C2: Maya uploads Transcript_SYN-24001_NYU and Transcript_SYN-24001_PSC | D2: 6 lines extracted; PSY 215 flagged quarter-system
A3: 2 | B3: Instant matches | C3: NYU PSYCH-UA 1, MATH-UA 121, ECON-UA 2 hit the equivalency table | D3: CAS PS 101, CAS MA 123, CAS EC 101; 4 units each; grade T
A4: 3 | B4: Quarter course | C4: PSC PSY 215 Psychology of Music, 4 qtr credits, B | D4: Elective CAS PS 2TR, 2.67 units
A5: 4 | B5: Maybe 1 | C5: NYU PSYCH-UA 10 with Syllabus_NYU_PSYCH-UA-10.pdf on file | D5: AI: ~75% overlap with CAS PS 211 -> evaluator decides (workbook: partial, statistics vs experimental design)
A6: 5 | B6: Maybe 2 | C6: NYU PSYCH-UA 25 Cognitive Neuroscience, no syllabus | D6: TS status; preliminary suggestion from description; reminders day 7/21/45
A7: 6 | B7: Evaluator | C7: Open PSYCH-UA 10; comparison already done; approve with reason code | D7: Decision saved, reusable = Yes
A8: 7 | B8: Late upload | C8: Maya uploads Syllabus_NYU_PSYCH-UA-25.pdf | D8: AI: ~62% overlap with CAS PS 231 -> evaluator decides (expected: elective CAS PS 2TR)
A9: 8 | B9: Posting | C9: Department -> Registrar -> MyBU-style CSV | D9: Secured credit updates; Liam's NYU PSYCH-UA 10 now matches instantly

Sheet Students
A1: Student ID | B1: Name | C1: Intended BU major | D1: BU school | E1: BU start term | F1: Story | G1: Transcript lines | H1: Units secured (matched) | I1: Units pending (maybe/review) | J1: No-credit lines | K1: Email | L1: Phone | M1: Address | N1: Previous school
A2: SYN-24001 | B2: Maya R. Delgado | C2: Psychology | D2: College of Arts & Sciences | E2: Fall 2026 | F2: Demo student from NYU: 6 courses (3 existing matches, 2 maybe, 1 summer quarter-system course) | G2: =COUNTIF('Transcript Lines'!$B$2:$B$57,A2) | H2: =SUMIFS('Transcript Lines'!$M$2:$M$57,'Transcript Lines'!$B$2:$B$57,A2,'Transcript Lines'!$K$2:$K$57,"Matched*") | I2: =SUMIFS('Transcript Lines'!$J$2:$J$57,'Transcript Lines'!$B$2:$B$57,A2,'Transcript Lines'!$K$2:$K$57,"Maybe*")+SUMIFS('Transcript Lines'!$J$2:$J$57,'Transcript Lines'!$B$2:$B$57,A2,'Transcript Lines'!$K$2:$K$57,"Pending*") | J2: =COUNTIFS('Transcript Lines'!$B$2:$B$57,A2,'Transcript Lines'!$N$2:$N$57,"TX") | K2: maya.delgado@example.edu | L2: 212-555-0141 | M2: 418 Quillfeather Row, Apt 3B, Brooklyn, NY 11215 | N2: NYU
A3: SYN-24002 | B3: Jordan A. Reyes | C3: Computer Science | D3: College of Arts & Sciences | E3: Fall 2026 | F3: From Northeastern. Rules showcase: C-, developmental math, P/F, 1-credit seminar, duplicate, CS Group C residency, 7-year-old course, incomplete syllabus | G3: =COUNTIF('Transcript Lines'!$B$2:$B$57,A3) | H3: =SUMIFS('Transcript Lines'!$M$2:$M$57,'Transcript Lines'!$B$2:$B$57,A3,'Transcript Lines'!$K$2:$K$57,"Matched*") | I3: =SUMIFS('Transcript Lines'!$J$2:$J$57,'Transcript Lines'!$B$2:$B$57,A3,'Transcript Lines'!$K$2:$K$57,"Maybe*")+SUMIFS('Transcript Lines'!$J$2:$J$57,'Transcript Lines'!$B$2:$B$57,A3,'Transcript Lines'!$K$2:$K$57,"Pending*") | J3: =COUNTIFS('Transcript Lines'!$B$2:$B$57,A3,'Transcript Lines'!$N$2:$N$57,"TX") | K3: jordan.reyes@example.edu | L3: 617-555-0122 | M3: 27 Thistlebrook Lane, Somerville, MA 02144 | N3: NEU
A4: SYN-24003 | B4: Aisha K. Bello | C4: Biology | D4: College of Arts & Sciences | E4: Fall 2026 | F4: From Northeastern. 5-credit lab courses; NU's one-semester general chemistry (maybe); research course; same-year conflicting decisions | G4: =COUNTIF('Transcript Lines'!$B$2:$B$57,A4) | H4: =SUMIFS('Transcript Lines'!$M$2:$M$57,'Transcript Lines'!$B$2:$B$57,A4,'Transcript Lines'!$K$2:$K$57,"Matched*") | I4: =SUMIFS('Transcript Lines'!$J$2:$J$57,'Transcript Lines'!$B$2:$B$57,A4,'Transcript Lines'!$K$2:$K$57,"Maybe*")+SUMIFS('Transcript Lines'!$J$2:$J$57,'Transcript Lines'!$B$2:$B$57,A4,'Transcript Lines'!$K$2:$K$57,"Pending*") | J4: =COUNTIFS('Transcript Lines'!$B$2:$B$57,A4,'Transcript Lines'!$N$2:$N$57,"TX") | K4: aisha.bello@example.edu | L4: 857-555-0163 | M4: 1190 Marrowind Avenue, Unit 2, Quincy, MA 02169 | N4: NEU
A5: SYN-24004 | B5: Liam O. Novak | C5: Economics | D5: College of Arts & Sciences | E5: Fall 2026 | F5: Northeastern then NYU (+ one non-accredited online school). 68-unit cap, ROTC, internship, superseded decision, prompt-injection syllabus, reuses Maya's approved course | G5: =COUNTIF('Transcript Lines'!$B$2:$B$57,A5) | H5: =SUMIFS('Transcript Lines'!$M$2:$M$57,'Transcript Lines'!$B$2:$B$57,A5,'Transcript Lines'!$K$2:$K$57,"Matched*") | I5: =SUMIFS('Transcript Lines'!$J$2:$J$57,'Transcript Lines'!$B$2:$B$57,A5,'Transcript Lines'!$K$2:$K$57,"Maybe*")+SUMIFS('Transcript Lines'!$J$2:$J$57,'Transcript Lines'!$B$2:$B$57,A5,'Transcript Lines'!$K$2:$K$57,"Pending*") | J5: =COUNTIFS('Transcript Lines'!$B$2:$B$57,A5,'Transcript Lines'!$N$2:$N$57,"TX") | K5: liam.novak@example.edu | L5: 646-555-0187 | M5: 62 Copperkettle Street, Apt 5F, Hoboken, NJ 07030 | N5: NYU
A7: Columns G-J are formulas over Transcript Lines. Units secured includes capped values; pending = units if approved.

Sheet Transcript Lines
A1: Line ID | B1: Student ID | C1: School | D1: Term | E1: Course code | F1: Title | G1: Credits | H1: Calendar | I1: Grade | J1: Units if approved | K1: Expected status | L1: Expected BU course | M1: Expected units | N1: Expected BU grade | O1: Expected reason code | P1: Flags | Q1: gt_counterpart | R1: gt_overlap_pct
A2: L-001 | B2: SYN-24001 | C2: NYU | D2: Fall 2024 | E2: PSYCH-UA 1 | F2: Intro to Psychology | G2: 4 | H2: Semester | I2: A- | J2: =IF(H2="Quarter",ROUND(G2*2/3,2),G2) | K2: Matched - existing equivalency | L2: CAS PS 101 | M2: 4 | N2: T | O2: EQ-CONTENT | Q2: CAS PS 101 | R2: 87
A3: L-002 | B3: SYN-24001 | C3: NYU | D3: Fall 2024 | E3: MATH-UA 121 | F3: Calculus I | G3: 4 | H3: Semester | I3: B+ | J3: =IF(H3="Quarter",ROUND(G3*2/3,2),G3) | K3: Matched - existing equivalency | L3: CAS MA 123 | M3: 4 | N3: T | O3: EQ-CONTENT | Q3: CAS MA 123 | R3: 100
A4: L-003 | B4: SYN-24001 | C4: NYU | D4: Fall 2024 | E4: ECON-UA 2 | F4: Introduction to Microeconomics | G4: 4 | H4: Semester | I4: B | J4: =IF(H4="Quarter",ROUND(G4*2/3,2),G4) | K4: Matched - existing equivalency | L4: CAS EC 101 | M4: 4 | N4: T | O4: EQ-CONTENT | Q4: CAS EC 101 | R4: 87
A5: L-004 | B5: SYN-24001 | C5: NYU | D5: Spring 2025 | E5: PSYCH-UA 10 | F5: Statistics for the Behavioral Sciences | G5: 4 | H5: Semester | I5: A | J5: =IF(H5="Quarter",ROUND(G5*2/3,2),G5) | K5: Maybe - syllabus on file; AI tier: Evaluator decides (50-79%) | M5: 0 | O5: PD-REVIEW | Q5: CAS PS 211 | R5: 75
A6: L-005 | B6: SYN-24001 | C6: NYU | D6: Spring 2025 | E6: PSYCH-UA 25 | F6: Cognitive Neuroscience | G6: 4 | H6: Semester | I6: B+ | J6: =IF(H6="Quarter",ROUND(G6*2/3,2),G6) | K6: Maybe - syllabus requested (TS) | M6: 0 | O6: PD-TS | Q6: CAS PS 231 | R6: 62
A7: L-006 | B7: SYN-24001 | C7: PSC | D7: Summer 2025 | E7: PSY 215 | F7: Psychology of Music | G7: 4 | H7: Quarter | I7: B | J7: =IF(H7="Quarter",ROUND(G7*2/3,2),G7) | K7: Matched - existing equivalency | L7: CAS PS 2TR | M7: 2.67 | N7: T | O7: EL-NOEQUIV
A8: L-007 | B8: SYN-24002 | C8: NEU | D8: Fall 2019 | E8: HIST 1130 | F8: Introduction to World History | G8: 4 | H8: Semester | I8: B | J8: =IF(H8="Quarter",ROUND(G8*2/3,2),G8) | K8: Pending - age review (5+ years old) | M8: 0 | O8: RV-AGE
A9: L-008 | B9: SYN-24002 | C9: NEU | D9: Fall 2023 | E9: CS 2000 | F9: Introduction to Program Design and Implementation | G9: 5 | H9: Semester | I9: A | J9: =IF(H9="Quarter",ROUND(G9*2/3,2),G9) | K9: Matched - existing equivalency | L9: CAS CS 111 | M9: 5 | N9: T | O9: EQ-CONTENT | Q9: CAS CS 111 | R9: 87
A10: L-009 | B10: SYN-24002 | C10: NEU | D10: Fall 2023 | E10: MATH 1341 | F10: Calculus 1 for Science and Engineering | G10: 4 | H10: Semester | I10: C- | J10: =IF(H10="Quarter",ROUND(G10*2/3,2),G10) | K10: Posted - no credit | L10: TFRGEN NOCRDT | M10: 0 | N10: TX | O10: NC-GRADE | Q10: CAS MA 123 | R10: 87
A11: L-010 | B11: SYN-24002 | C11: NEU | D11: Fall 2023 | E11: MATH 0990 | F11: Algebra Foundations (developmental) | G11: 4 | H11: Semester | I11: A | J11: =IF(H11="Quarter",ROUND(G11*2/3,2),G11) | K11: Posted - no credit | L11: TFRGEN NOCRDT | M11: 0 | N11: TX | O11: NC-REMEDIAL
A12: L-011 | B12: SYN-24002 | C12: NEU | D12: Fall 2023 | E12: PE 1100 | F12: Fitness Fundamentals | G12: 2 | H12: Semester | I12: P | J12: =IF(H12="Quarter",ROUND(G12*2/3,2),G12) | K12: Posted - no credit | L12: TFRGEN NOCRDT | M12: 0 | N12: TX | O12: NC-PE
A13: L-012 | B13: SYN-24002 | C13: NEU | D13: Fall 2023 | E13: FYS 1000 | F13: First-Year Seminar | G13: 1 | H13: Semester | I13: A | J13: =IF(H13="Quarter",ROUND(G13*2/3,2),G13) | K13: Posted - no credit | L13: TFRGEN NOCRDT | M13: 0 | N13: TX | O13: NC-ONECREDIT
A14: L-013 | B14: SYN-24002 | C14: NEU | D14: Spring 2024 | E14: CS 2100 | F14: Program Design and Implementation 1 | G14: 5 | H14: Semester | I14: B+ | J14: =IF(H14="Quarter",ROUND(G14*2/3,2),G14) | K14: Maybe - syllabus on file; AI tier: Evaluator decides (50-79%) | M14: 0 | O14: PD-REVIEW | Q14: CAS CS 112 | R14: 62
A15: L-014 | B15: SYN-24002 | C15: NEU | D15: Spring 2024 | E15: CS 1800 | F15: Discrete Structures | G15: 4 | H15: Semester | I15: B | J15: =IF(H15="Quarter",ROUND(G15*2/3,2),G15) | K15: Matched - existing equivalency | L15: CAS CS 131 | M15: 4 | N15: T | O15: EQ-CONTENT | Q15: CAS CS 131 | R15: 87
A16: L-015 | B16: SYN-24002 | C16: NEU | D16: Spring 2024 | E16: CS 1990 | F16: Introduction to Programming in Python | G16: 4 | H16: Semester | I16: A- | J16: =IF(H16="Quarter",ROUND(G16*2/3,2),G16) | K16: Matched - existing equivalency | L16: CAS CS 1TR | M16: 4 | N16: T | O16: EL-DUPLICATE | Q16: CAS CS 111 | R16: 75
A17: L-016 | B17: SYN-24002 | C17: NEU | D17: Spring 2024 | E17: FILM 1101 | F17: Film Analysis | G17: 4 | H17: Semester | I17: P | J17: =IF(H17="Quarter",ROUND(G17*2/3,2),G17) | K17: Posted - no credit | L17: TFRGEN NOCRDT | M17: 0 | N17: TX | O17: NC-PASSFAIL
A18: L-017 | B18: SYN-24002 | C18: NEU | D18: Fall 2024 | E18: CS 2700 | F18: Data Structures and Analysis | G18: 5 | H18: Semester | I18: B | J18: =IF(H18="Quarter",ROUND(G18*2/3,2),G18) | K18: Maybe - syllabus incomplete (TM request) | M18: 0 | O18: PD-TM | Q18: CAS CS 112 | R18: 75
A19: L-018 | B19: SYN-24002 | C19: NEU | D19: Fall 2024 | E19: CS 3650 | F19: Computer Systems | G19: 4 | H19: Semester | I19: B | J19: =IF(H19="Quarter",ROUND(G19*2/3,2),G19) | K19: Matched - existing equivalency | L19: CAS CS 210 | M19: 4 | N19: T | O19: EQ-CONTENT | Q19: CAS CS 210 | R19: 100
A20: L-019 | B20: SYN-24002 | C20: NEU | D20: Fall 2024 | E20: CS 4400 | F20: Programming Languages | G20: 4 | H20: Semester | I20: A- | J20: =IF(H20="Quarter",ROUND(G20*2/3,2),G20) | K20: Matched - existing equivalency | L20: CAS CS 2TR | M20: 4 | N20: T | O20: EL-RESIDENCY | Q20: CAS CS 320 | R20: 100
A21: L-020 | B21: SYN-24002 | C21: NEU | D21: Fall 2024 | E21: MATH 2331 | F21: Linear Algebra | G21: 4 | H21: Semester | I21: B+ | J21: =IF(H21="Quarter",ROUND(G21*2/3,2),G21) | K21: Matched - existing equivalency | L21: CAS MA 242 | M21: 4 | N21: T | O21: EQ-CONTENT | Q21: CAS MA 242 | R21: 100
A22: L-021 | B22: SYN-24003 | C22: NEU | D22: Fall 2024 | E22: BIOL 1107 | F22: Foundations of Biology | G22: 5 | H22: Semester | I22: A | J22: =IF(H22="Quarter",ROUND(G22*2/3,2),G22) | K22: Matched - existing equivalency | L22: CAS BI 107 | M22: 5 | N22: T | O22: EQ-CONTENT | Q22: CAS BI 107 | R22: 87
A23: L-022 | B23: SYN-24003 | C23: NEU | D23: Fall 2024 | E23: CHEM 1161 | F23: General Chemistry for Science Majors | G23: 5 | H23: Semester | I23: B+ | J23: =IF(H23="Quarter",ROUND(G23*2/3,2),G23) | K23: Maybe - syllabus on file; AI tier: Evaluator decides (50-79%) | M23: 0 | O23: PD-REVIEW | Q23: CAS CH 101 | R23: 62
A24: L-023 | B24: SYN-24003 | C24: NEU | D24: Fall 2024 | E24: ENGW 1111 | F24: First-Year Writing | G24: 4 | H24: Semester | I24: A- | J24: =IF(H24="Quarter",ROUND(G24*2/3,2),G24) | K24: Matched - existing equivalency | L24: TFRGEN 1TR | M24: 4 | N24: T | O24: EL-NOEQUIV
A25: L-024 | B25: SYN-24003 | C25: NEU | D25: Spring 2025 | E25: BIOL 1113 | F25: General Biology 2 | G25: 4 | H25: Semester | I25: B+ | J25: =IF(H25="Quarter",ROUND(G25*2/3,2),G25) | K25: Matched - existing equivalency | L25: CAS BI 108 | M25: 4 | N25: T | O25: EQ-CONTENT | Q25: CAS BI 108 | R25: 100
A26: L-025 | B26: SYN-24003 | C26: NEU | D26: Spring 2025 | E26: MATH 1341 | F26: Calculus 1 for Science and Engineering | G26: 4 | H26: Semester | I26: A | J26: =IF(H26="Quarter",ROUND(G26*2/3,2),G26) | K26: Matched - existing equivalency | L26: CAS MA 123 | M26: 4 | N26: T | O26: EQ-CONTENT | Q26: CAS MA 123 | R26: 87
A27: L-026 | B27: SYN-24003 | C27: NEU | D27: Spring 2025 | E27: BIOL 2299 | F27: Inquiries in Biological Sciences | G27: 4 | H27: Semester | I27: B | J27: =IF(H27="Quarter",ROUND(G27*2/3,2),G27) | K27: Maybe - syllabus on file; AI tier: Elective (<50%) | M27: 0 | O27: PD-REVIEW | Q27: CAS BI 107 | R27: 37
A28: L-027 | B28: SYN-24003 | C28: NEU | D28: Fall 2025 | E28: BIOL 2301 | F28: Genetics and Molecular Biology | G28: 5 | H28: Semester | I28: B+ | J28: =IF(H28="Quarter",ROUND(G28*2/3,2),G28) | K28: Maybe - syllabus on file; AI tier: Evaluator decides (50-79%) | M28: 0 | O28: PD-REVIEW | Q28: CAS BI 206 | R28: 75
A29: L-028 | B29: SYN-24003 | C29: NEU | D29: Fall 2025 | E29: CHEM 2311 | F29: Organic Chemistry 1 | G29: 5 | H29: Semester | I29: C+ | J29: =IF(H29="Quarter",ROUND(G29*2/3,2),G29) | K29: Maybe - syllabus requested (TS) | M29: 0 | O29: PD-TS | Q29: CAS CH 203 | R29: 87
A30: L-029 | B30: SYN-24003 | C30: NEU | D30: Fall 2025 | E30: BIOL 2703 | F30: Microbiology | G30: 5 | H30: Semester | I30: A- | J30: =IF(H30="Quarter",ROUND(G30*2/3,2),G30) | K30: Matched - existing equivalency | L30: CAS BI 2TR | M30: 5 | N30: T | O30: EL-PARTIAL | P30: CONFLICT: same catalog year, different decisions -> flag for department | Q30: CAS BI 210 | R30: 87
A31: L-030 | B31: SYN-24003 | C31: NEU | D31: Spring 2026 | E31: BIOL 3611 | F31: Biochemistry | G31: 5 | H31: Semester | I31: B+ | J31: =IF(H31="Quarter",ROUND(G31*2/3,2),G31) | K31: Maybe - syllabus on file; AI tier: Equivalent (>=80%) | M31: 0 | O31: PD-REVIEW | Q31: CAS CH 373 | R31: 87
A32: L-031 | B32: SYN-24003 | C32: NEU | D32: Spring 2026 | E32: CHEM 2313 | F32: Organic Chemistry 2 | G32: 5 | H32: Semester | I32: B | J32: =IF(H32="Quarter",ROUND(G32*2/3,2),G32) | K32: Matched - existing equivalency | L32: CAS CH 204 | M32: 5 | N32: T | O32: EQ-CONTENT | Q32: CAS CH 204 | R32: 100
A33: L-032 | B33: SYN-24003 | C33: NEU | D33: Spring 2026 | E33: BIOL 4990 | F33: Directed Research in Biology | G33: 4 | H33: Semester | I33: A | J33: =IF(H33="Quarter",ROUND(G33*2/3,2),G33) | K33: Posted - no credit | L33: TFRGEN NOCRDT | M33: 0 | N33: TX | O33: NC-RESEARCH
A34: L-033 | B34: SYN-24004 | C34: NEU | D34: Fall 2022 | E34: ECON 1116 | F34: Principles of Microeconomics | G34: 4 | H34: Semester | I34: A | J34: =IF(H34="Quarter",ROUND(G34*2/3,2),G34) | K34: Matched - existing equivalency | L34: CAS EC 101 | M34: 4 | N34: T | O34: EQ-CONTENT | Q34: CAS EC 101 | R34: 87
A35: L-034 | B35: SYN-24004 | C35: NEU | D35: Fall 2022 | E35: MATH 1341 | F35: Calculus 1 for Science and Engineering | G35: 4 | H35: Semester | I35: B | J35: =IF(H35="Quarter",ROUND(G35*2/3,2),G35) | K35: Matched - existing equivalency | L35: CAS MA 123 | M35: 4 | N35: T | O35: EQ-CONTENT | Q35: CAS MA 123 | R35: 87
A36: L-035 | B36: SYN-24004 | C36: NEU | D36: Fall 2022 | E36: ENGW 1111 | F36: First-Year Writing | G36: 4 | H36: Semester | I36: A- | J36: =IF(H36="Quarter",ROUND(G36*2/3,2),G36) | K36: Matched - existing equivalency | L36: TFRGEN 1TR | M36: 4 | N36: T | O36: EL-NOEQUIV
A37: L-036 | B37: SYN-24004 | C37: NEU | D37: Fall 2022 | E37: MILS 1101 | F37: Military Science I (ROTC) | G37: 2 | H37: Semester | I37: A | J37: =IF(H37="Quarter",ROUND(G37*2/3,2),G37) | K37: Posted - no credit | L37: TFRGEN NOCRDT | M37: 0 | N37: TX | O37: NC-ROTC
A38: L-037 | B38: SYN-24004 | C38: NEU | D38: Spring 2023 | E38: ECON 1115 | F38: Principles of Macroeconomics | G38: 4 | H38: Semester | I38: B+ | J38: =IF(H38="Quarter",ROUND(G38*2/3,2),G38) | K38: Matched - existing equivalency | L38: CAS EC 102 | M38: 4 | N38: T | O38: EQ-CONTENT | Q38: CAS EC 102 | R38: 100
A39: L-038 | B39: SYN-24004 | C39: NEU | D39: Spring 2023 | E39: MATH 1342 | F39: Calculus 2 for Science and Engineering | G39: 4 | H39: Semester | I39: B- | J39: =IF(H39="Quarter",ROUND(G39*2/3,2),G39) | K39: Matched - existing equivalency | L39: CAS MA 124 | M39: 4 | N39: T | O39: EQ-CONTENT | Q39: CAS MA 124 | R39: 87
A40: L-039 | B40: SYN-24004 | C40: NEU | D40: Spring 2023 | E40: HIST 1130 | F40: Introduction to World History | G40: 4 | H40: Semester | I40: B | J40: =IF(H40="Quarter",ROUND(G40*2/3,2),G40) | K40: Matched - existing equivalency | L40: TFRGEN 1TR | M40: 4 | N40: T | O40: EL-NOEQUIV
A41: L-040 | B41: SYN-24004 | C41: NEU | D41: Spring 2023 | E41: SOCL 1101 | F41: Introduction to Sociology | G41: 4 | H41: Semester | I41: A | J41: =IF(H41="Quarter",ROUND(G41*2/3,2),G41) | K41: Matched - existing equivalency | L41: TFRGEN 1TR | M41: 4 | N41: T | O41: EL-NOEQUIV
A42: L-041 | B42: SYN-24004 | C42: SOI | D42: Summer 2023 | E42: ECO 210 | F42: Personal Finance | G42: 3 | H42: Semester | I42: A | J42: =IF(H42="Quarter",ROUND(G42*2/3,2),G42) | K42: Posted - no credit | L42: TFRGEN NOCRDT | M42: 0 | N42: TX | O42: NC-ACCRED
A43: L-042 | B43: SYN-24004 | C43: SOI | D43: Summer 2023 | E43: BUS 101 | F43: Introduction to Business | G43: 3 | H43: Semester | I43: A | J43: =IF(H43="Quarter",ROUND(G43*2/3,2),G43) | K43: Posted - no credit | L43: TFRGEN NOCRDT | M43: 0 | N43: TX | O43: NC-ACCRED
A44: L-043 | B44: SYN-24004 | C44: NYU | D44: Fall 2023 | E44: PSYCH-UA 10 | F44: Statistics for the Behavioral Sciences | G44: 4 | H44: Semester | I44: B+ | J44: =IF(H44="Quarter",ROUND(G44*2/3,2),G44) | K44: Maybe - syllabus on file; AI tier: Evaluator decides (50-79%) | M44: 0 | O44: PD-REVIEW | P44: Same course as Maya's PSYCH-UA 10: matches instantly once her decision is approved (test T15) | Q44: CAS PS 211 | R44: 75
A45: L-044 | B45: SYN-24004 | C45: NYU | D45: Fall 2023 | E45: COMM-UA 10 | F45: Public Speaking | G45: 4 | H45: Semester | I45: A- | J45: =IF(H45="Quarter",ROUND(G45*2/3,2),G45) | K45: Matched - existing equivalency | L45: TFRGEN 1TR | M45: 4 | N45: T | O45: EL-NOEQUIV
A46: L-045 | B46: SYN-24004 | C46: NYU | D46: Fall 2023 | E46: ART-UA 5 | F46: Art Appreciation | G46: 4 | H46: Semester | I46: B+ | J46: =IF(H46="Quarter",ROUND(G46*2/3,2),G46) | K46: Matched - existing equivalency | L46: TFRGEN 1TR | M46: 4 | N46: T | O46: EL-NOEQUIV
A47: L-046 | B47: SYN-24004 | C47: NYU | D47: Spring 2024 | E47: SPAN-UA 1 | F47: Elementary Spanish I | G47: 4 | H47: Semester | I47: B | J47: =IF(H47="Quarter",ROUND(G47*2/3,2),G47) | K47: Matched - existing equivalency | L47: TFRGEN 1TR | M47: 4 | N47: T | O47: EL-NOEQUIV
A48: L-047 | B48: SYN-24004 | C48: NYU | D48: Spring 2024 | E48: ECON-UA 10 | F48: Intermediate Microeconomics | G48: 4 | H48: Semester | I48: B+ | J48: =IF(H48="Quarter",ROUND(G48*2/3,2),G48) | K48: Matched - existing equivalency | L48: CAS EC 201 | M48: 4 | N48: T | O48: EQ-CONTENT | P48: Econ 200+ cap applies only after matriculation: not applied | Q48: CAS EC 201 | R48: 87
A49: L-048 | B49: SYN-24004 | C49: NYU | D49: Spring 2024 | E49: PHIL-UA 3 | F49: Introduction to Ethics | G49: 4 | H49: Semester | I49: A | J49: =IF(H49="Quarter",ROUND(G49*2/3,2),G49) | K49: Matched - existing equivalency | L49: TFRGEN 1TR | M49: 4 | N49: T | O49: EL-NOEQUIV
A50: L-049 | B50: SYN-24004 | C50: NYU | D50: Fall 2024 | E50: ECON-UA 12 | F50: Intermediate Macroeconomics | G50: 4 | H50: Semester | I50: B | J50: =IF(H50="Quarter",ROUND(G50*2/3,2),G50) | K50: Matched - existing equivalency | L50: CAS EC 202 | M50: 4 | N50: T | O50: EQ-CONTENT | P50: Econ 200+ cap applies only after matriculation: not applied | Q50: CAS EC 202 | R50: 100
A51: L-050 | B51: SYN-24004 | C51: NYU | D51: Fall 2024 | E51: ECON-UA 18 | F51: Statistics | G51: 4 | H51: Semester | I51: A- | J51: =IF(H51="Quarter",ROUND(G51*2/3,2),G51) | K51: Matched - existing equivalency | L51: CAS EC 203 | M51: 4 | N51: T | O51: EQ-EVALUATOR | P51: Older conflicting decision superseded by newest catalog year; Econ 200+ cap applies only after matriculation: not applied | Q51: CAS EC 203 | R51: 100
A52: L-051 | B52: SYN-24004 | C52: NYU | D52: Fall 2024 | E52: MATH-UA 140 | F52: Linear Algebra | G52: 4 | H52: Semester | I52: B | J52: =IF(H52="Quarter",ROUND(G52*2/3,2),G52) | K52: Matched - existing equivalency | L52: CAS MA 242 | M52: 4 | N52: T | O52: EQ-CONTENT | Q52: CAS MA 242 | R52: 100
A53: L-052 | B53: SYN-24004 | C53: NYU | D53: Spring 2025 | E53: ECON-UA 266 | F53: Intro to Econometrics | G53: 4 | H53: Semester | I53: B | J53: =IF(H53="Quarter",ROUND(G53*2/3,2),G53) | K53: Maybe - syllabus on file; AI tier: Evaluator decides (50-79%) | M53: 0 | O53: PD-REVIEW | P53: Econ 200+ cap applies only after matriculation: not applied | Q53: CAS EC 204 | R53: 62
A54: L-053 | B54: SYN-24004 | C54: NYU | D54: Spring 2025 | E54: ECON-UA 163 | F54: Money and Banking | G54: 4 | H54: Semester | I54: A- | J54: =IF(H54="Quarter",ROUND(G54*2/3,2),G54) | K54: Matched - existing equivalency | L54: CAS EC 220 | M54: 0 | N54: T | O54: EQ-CONTENT | P54: 68-unit cap reached: only 0.0 of 4.0 units can count; Econ 200+ cap applies only after matriculation: not applied | Q54: CAS EC 220 | R54: 100
A55: L-054 | B55: SYN-24004 | C55: NYU | D55: Fall 2025 | E55: ECON-UA 166 | F55: International Trade | G55: 4 | H55: Semester | I55: B+ | J55: =IF(H55="Quarter",ROUND(G55*2/3,2),G55) | K55: Matched - existing equivalency | L55: CAS EC 250 | M55: 0 | N55: T | O55: EQ-CONTENT | P55: 68-unit cap reached: only 0.0 of 4.0 units can count; Econ 200+ cap applies only after matriculation: not applied | Q55: CAS EC 250 | R55: 87
A56: L-055 | B56: SYN-24004 | C56: NYU | D56: Fall 2025 | E56: ECON-UA 169 | F56: Labor Economics | G56: 4 | H56: Semester | I56: B | J56: =IF(H56="Quarter",ROUND(G56*2/3,2),G56) | K56: Maybe - syllabus requested (TS) | M56: 0 | O56: PD-TS | P56: 68-unit cap reached: only 0.0 of 4.0 units can count; Econ 200+ cap applies only after matriculation: not applied | Q56: CAS EC 240 | R56: 75
A57: L-056 | B57: SYN-24004 | C57: NYU | D57: Spring 2026 | E57: ECON-UA 980 | F57: Economics Internship | G57: 4 | H57: Semester | I57: P | J57: =IF(H57="Quarter",ROUND(G57*2/3,2),G57) | K57: Posted - no credit | L57: TFRGEN NOCRDT | M57: 0 | N57: TX | O57: NC-INTERNSHIP

Sheet BU Courses
A1: BU code | B1: Dept | C1: Title | D1: Program | E1: Requirement type | F1: Level | G1: Credits | H1: Residency rule | I1: Source | J1: Description | K1: Learning outcomes | L1: Topics
A2: CAS CS 111 | B2: CS | C2: Introduction to Computer Science 1 | D2: Computer Science | E2: Core (Group A) | F2: 100 | G2: 4 | I2: Code/title from provided BU workbook (public catalog); description synthetic | J2: Introduction to Computer Science 1 is an introductory course in computer science. It covers variables and expressions, conditionals and loops, functions and parameters and lists and strings, and builds toward recursion and file input and output. Students work through programming assignments, with later units on debugging and testing and problem decomposition. | K2: Explain the core ideas of variables and expressions | Apply conditionals and loops to solve standard problems | Analyze problems involving functions and parameters | Use lists and strings in practical exercises | Evaluate approaches to recursion | Communicate findings about file input and output | L2: variables and expressions | conditionals and loops | functions and parameters | lists and strings | recursion | file input and output | debugging and testing | problem decomposition
A3: CAS CS 112 | B3: CS | C3: Introduction to Computer Science 2 | D3: Computer Science | E3: Core (Group A) | F3: 100 | G3: 4 | I3: Code/title from provided BU workbook (public catalog); description synthetic | J3: Introduction to Computer Science 2 is an introductory course in computer science. It covers object-oriented programming, linked lists, stacks and queues and binary trees, and builds toward hash tables and sorting algorithms. Students work through programming assignments, with later units on algorithm efficiency and recursion on data structures. | K3: Explain the core ideas of object-oriented programming | Apply linked lists to solve standard problems | Analyze problems involving stacks and queues | Use binary trees in practical exercises | Evaluate approaches to hash tables | Communicate findings about sorting algorithms | L3: object-oriented programming | linked lists | stacks and queues | binary trees | hash tables | sorting algorithms | algorithm efficiency | recursion on data structures
A4: CAS CS 131 | B4: CS | C4: Combinatoric Structures | D4: Computer Science | E4: Core (Group A) | F4: 100 | G4: 4 | I4: Code/title from provided BU workbook (public catalog); description synthetic | J4: Combinatoric Structures is an introductory course in computer science. It covers propositional logic, proof techniques, sets and functions and counting principles, and builds toward mathematical induction and relations. Students work through programming assignments, with later units on graph basics and discrete probability. | K4: Explain the core ideas of propositional logic | Apply proof techniques to solve standard problems | Analyze problems involving sets and functions | Use counting principles in practical exercises | Evaluate approaches to mathematical induction | Communicate findings about relations | L4: propositional logic | proof techniques | sets and functions | counting principles | mathematical induction | relations | graph basics | discrete probability
A5: CAS CS 210 | B5: CS | C5: Computer Systems | D5: Computer Science | E5: Core (Group A) | F5: 200 | G5: 4 | I5: Code/title from provided BU workbook (public catalog); description synthetic | J5: Computer Systems is an intermediate course in computer science. It covers binary data representation, C programming, assembly language and memory hierarchy, and builds toward caches and linking and loading. Students work through programming assignments, with later units on processes and virtual memory. | K5: Explain the core ideas of binary data representation | Apply C programming to solve standard problems | Analyze problems involving assembly language | Use memory hierarchy in practical exercises | Evaluate approaches to caches | Communicate findings about linking and loading | L5: binary data representation | C programming | assembly language | memory hierarchy | caches | linking and loading | processes | virtual memory
A6: CAS CS 330 | B6: CS | C6: Introduction to the Analysis of Algorithms | D6: Computer Science | E6: Core (Group A) | F6: 300 | G6: 4 | I6: Code/title from provided BU workbook (public catalog); description synthetic | J6: Introduction to the Analysis of Algorithms is an advanced course in computer science. It covers asymptotic analysis, divide and conquer, greedy algorithms and dynamic programming, and builds toward graph algorithms and shortest paths. Students work through programming assignments, with later units on network flow and NP-completeness. | K6: Explain the core ideas of asymptotic analysis | Apply divide and conquer to solve standard problems | Analyze problems involving greedy algorithms | Use dynamic programming in practical exercises | Evaluate approaches to graph algorithms | Communicate findings about shortest paths | L6: asymptotic analysis | divide and conquer | greedy algorithms | dynamic programming | graph algorithms | shortest paths | network flow | NP-completeness
A7: CAS CS 132 | B7: CS | C7: Geometric Algorithms | D7: Computer Science | E7: Group B (choose) | F7: 100 | G7: 4 | I7: Code/title from provided BU workbook (public catalog); description synthetic | J7: Geometric Algorithms is an introductory course in computer science. It covers vectors and matrices, linear systems, matrix factorization and eigenvalues, and builds toward least squares and geometric transformations. Students work through programming assignments, with later units on singular value decomposition and computational geometry. | K7: Explain the core ideas of vectors and matrices | Apply linear systems to solve standard problems | Analyze problems involving matrix factorization | Use eigenvalues in practical exercises | Evaluate approaches to least squares | Communicate findings about geometric transformations | L7: vectors and matrices | linear systems | matrix factorization | eigenvalues | least squares | geometric transformations | singular value decomposition | computational geometry
A8: CAS CS 235 | B8: CS | C8: Algebraic Algorithms | D8: Computer Science | E8: Group B (choose) | F8: 200 | G8: 4 | I8: Code/title from provided BU workbook (public catalog); description synthetic | J8: Algebraic Algorithms is an intermediate course in computer science. It covers modular arithmetic, groups and rings, polynomials and finite fields, and builds toward public-key cryptography and error-correcting codes. Students work through programming assignments, with later units on number-theoretic algorithms and fast Fourier transform. | K8: Explain the core ideas of modular arithmetic | Apply groups and rings to solve standard problems | Analyze problems involving polynomials | Use finite fields in practical exercises | Evaluate approaches to public-key cryptography | Communicate findings about error-correcting codes | L8: modular arithmetic | groups and rings | polynomials | finite fields | public-key cryptography | error-correcting codes | number-theoretic algorithms | fast Fourier transform
A9: CAS CS 237 | B9: CS | C9: Probability in Computing | D9: Computer Science | E9: Group B (choose) | F9: 200 | G9: 4 | I9: Code/title from provided BU workbook (public catalog); description synthetic | J9: Probability in Computing is an intermediate course in computer science. It covers probability axioms, random variables, expectation and variance and common distributions, and builds toward Markov chains and randomized algorithms. Students work through programming assignments, with later units on tail bounds and simulation. | K9: Explain the core ideas of probability axioms | Apply random variables to solve standard problems | Analyze problems involving expectation and variance | Use common distributions in practical exercises | Evaluate approaches to Markov chains | Communicate findings about randomized algorithms | L9: probability axioms | random variables | expectation and variance | common distributions | Markov chains | randomized algorithms | tail bounds | simulation
A10: CAS CS 320 | B10: CS | C10: Concepts of Programming Languages | D10: Computer Science | E10: Group C (BU only) | F10: 300 | G10: 4 | H10: CS Group C: must be taken at BU (requirement blocked; units may post as elective) | I10: Code/title from provided BU workbook (public catalog); description synthetic | J10: Concepts of Programming Languages is an advanced course in computer science. It covers syntax and grammars, interpreters, type systems and functional programming, and builds toward scoping and binding and parsing. Students work through programming assignments, with later units on semantics and language paradigms. | K10: Explain the core ideas of syntax and grammars | Apply interpreters to solve standard problems | Analyze problems involving type systems | Use functional programming in practical exercises | Evaluate approaches to scoping and binding | Communicate findings about parsing | L10: syntax and grammars | interpreters | type systems | functional programming | scoping and binding | parsing | semantics | language paradigms
A11: CAS CS 332 | B11: CS | C11: Elements of the Theory of Computation | D11: Computer Science | E11: Group C (BU only) | F11: 300 | G11: 4 | H11: CS Group C: must be taken at BU (requirement blocked; units may post as elective) | I11: Code/title from provided BU workbook (public catalog); description synthetic | J11: Elements of the Theory of Computation is an advanced course in computer science. It covers finite automata, regular languages, context-free grammars and pushdown automata, and builds toward Turing machines and decidability. Students work through programming assignments, with later units on reductions and complexity classes. | K11: Explain the core ideas of finite automata | Apply regular languages to solve standard problems | Analyze problems involving context-free grammars | Use pushdown automata in practical exercises | Evaluate approaches to Turing machines | Communicate findings about decidability | L11: finite automata | regular languages | context-free grammars | pushdown automata | Turing machines | decidability | reductions | complexity classes
A12: CAS CS 350 | B12: CS | C12: Fundamentals of Computing Systems | D12: Computer Science | E12: Group C (BU only) | F12: 300 | G12: 4 | H12: CS Group C: must be taken at BU (requirement blocked; units may post as elective) | I12: Code/title from provided BU workbook (public catalog); description synthetic | J12: Fundamentals of Computing Systems is an advanced course in computer science. It covers concurrency, scheduling, synchronization and queueing models, and builds toward performance analysis and operating system design. Students work through programming assignments, with later units on resource management and distributed coordination. | K12: Explain the core ideas of concurrency | Apply scheduling to solve standard problems | Analyze problems involving synchronization | Use queueing models in practical exercises | Evaluate approaches to performance analysis | Communicate findings about operating system design | L12: concurrency | scheduling | synchronization | queueing models | performance analysis | operating system design | resource management | distributed coordination
A13: CAS CS 103 | B13: CS | C13: Introduction to Internet Technologies | D13: Computer Science | E13: Elective | F13: 100 | G13: 4 | I13: Fully synthetic course (not a real BU offering) | J13: Introduction to Internet Technologies is an introductory course in computer science. It covers how the internet works, HTML, CSS and web hosting, and builds toward client-server model and basic JavaScript. Students work through programming assignments, with later units on web accessibility and online privacy. | K13: Explain the core ideas of how the internet works | Apply HTML to solve standard problems | Analyze problems involving CSS | Use web hosting in practical exercises | Evaluate approaches to client-server model | Communicate findings about basic JavaScript | L13: how the internet works | HTML | CSS | web hosting | client-server model | basic JavaScript | web accessibility | online privacy
A14: CAS CS 108 | B14: CS | C14: Programming with Python | D14: Computer Science | E14: Elective | F14: 100 | G14: 4 | I14: Fully synthetic course (not a real BU offering) | J14: Programming with Python is an introductory course in computer science. It covers Python syntax, control flow, functions and lists and dictionaries, and builds toward modules and libraries and file processing. Students work through programming assignments, with later units on data visualization and scripting automation. | K14: Explain the core ideas of Python syntax | Apply control flow to solve standard problems | Analyze problems involving functions | Use lists and dictionaries in practical exercises | Evaluate approaches to modules and libraries | Communicate findings about file processing | L14: Python syntax | control flow | functions | lists and dictionaries | modules and libraries | file processing | data visualization | scripting automation
A15: CAS CS 115 | B15: CS | C15: Introduction to Data Science | D15: Computer Science | E15: Elective | F15: 100 | G15: 4 | I15: Fully synthetic course (not a real BU offering) | J15: Introduction to Data Science is an introductory course in computer science. It covers data collection, data cleaning, exploratory analysis and data visualization, and builds toward descriptive statistics and regression basics. Students work through programming assignments, with later units on Python notebooks and data ethics. | K15: Explain the core ideas of data collection | Apply data cleaning to solve standard problems | Analyze problems involving exploratory analysis | Use data visualization in practical exercises | Evaluate approaches to descriptive statistics | Communicate findings about regression basics | L15: data collection | data cleaning | exploratory analysis | data visualization | descriptive statistics | regression basics | Python notebooks | data ethics
A16: CAS CS 122 | B16: CS | C16: Web Development Foundations | D16: Computer Science | E16: Elective | F16: 100 | G16: 4 | I16: Fully synthetic course (not a real BU offering) | J16: Web Development Foundations is an introductory course in computer science. It covers HTML, CSS, JavaScript and DOM manipulation, and builds toward responsive design and forms and validation. Students work through programming assignments, with later units on HTTP basics and version control. | K16: Explain the core ideas of HTML | Apply CSS to solve standard problems | Analyze problems involving JavaScript | Use DOM manipulation in practical exercises | Evaluate approaches to responsive design | Communicate findings about forms and validation | L16: HTML | CSS | JavaScript | DOM manipulation | responsive design | forms and validation | HTTP basics | version control
A17: CAS CS 140 | B17: CS | C17: Introduction to Cybersecurity | D17: Computer Science | E17: Elective | F17: 100 | G17: 4 | I17: Fully synthetic course (not a real BU offering) | J17: Introduction to Cybersecurity is an introductory course in computer science. It covers threat models, cryptography basics, authentication and network attacks, and builds toward malware and secure coding. Students work through programming assignments, with later units on security policy and incident response. | K17: Explain the core ideas of threat models | Apply cryptography basics to solve standard problems | Analyze problems involving authentication | Use network attacks in practical exercises | Evaluate approaches to malware | Communicate findings about secure coding | L17: threat models | cryptography basics | authentication | network attacks | malware | secure coding | security policy | incident response
A18: CAS CS 211 | B18: CS | C18: Object-Oriented Software Design | D18: Computer Science | E18: Elective | F18: 200 | G18: 4 | I18: Fully synthetic course (not a real BU offering) | J18: Object-Oriented Software Design is an intermediate course in computer science. It covers object-oriented programming, classes and interfaces, inheritance and design patterns, and builds toward UML modeling and unit testing. Students work through programming assignments, with later units on refactoring and version control. | K18: Explain the core ideas of object-oriented programming | Apply classes and interfaces to solve standard problems | Analyze problems involving inheritance | Use design patterns in practical exercises | Evaluate approaches to UML modeling | Communicate findings about unit testing | L18: object-oriented programming | classes and interfaces | inheritance | design patterns | UML modeling | unit testing | refactoring | version control
A19: CAS CS 216 | B19: CS | C19: Database Systems | D19: Computer Science | E19: Elective | F19: 200 | G19: 4 | I19: Fully synthetic course (not a real BU offering) | J19: Database Systems is an intermediate course in computer science. It covers relational model, SQL queries, entity-relationship design and normalization, and builds toward indexing and transactions. Students work through programming assignments, with later units on query optimization and NoSQL databases. | K19: Explain the core ideas of relational model | Apply SQL queries to solve standard problems | Analyze problems involving entity-relationship design | Use normalization in practical exercises | Evaluate approaches to indexing | Communicate findings about transactions | L19: relational model | SQL queries | entity-relationship design | normalization | indexing | transactions | query optimization | NoSQL databases
A20: CAS CS 225 | B20: CS | C20: Computer Networks Fundamentals | D20: Computer Science | E20: Elective | F20: 200 | G20: 4 | I20: Fully synthetic course (not a real BU offering) | J20: Computer Networks Fundamentals is an intermediate course in computer science. It covers network layers, TCP and UDP, IP addressing and routing, and builds toward the web and HTTP and wireless networks. Students work through programming assignments, with later units on network security and socket programming. | K20: Explain the core ideas of network layers | Apply TCP and UDP to solve standard problems | Analyze problems involving IP addressing | Use routing in practical exercises | Evaluate approaches to the web and HTTP | Communicate findings about wireless networks | L20: network layers | TCP and UDP | IP addressing | routing | the web and HTTP | wireless networks | network security | socket programming
A21: CAS CS 236 | B21: CS | C21: Information Security | D21: Computer Science | E21: Elective | F21: 200 | G21: 4 | I21: Fully synthetic course (not a real BU offering) | J21: Information Security is an intermediate course in computer science. It covers cryptography basics, access control, authentication and software vulnerabilities, and builds toward network attacks and secure coding. Students work through programming assignments, with later units on privacy and security policy. | K21: Explain the core ideas of cryptography basics | Apply access control to solve standard problems | Analyze problems involving authentication | Use software vulnerabilities in practical exercises | Evaluate approaches to network attacks | Communicate findings about secure coding | L21: cryptography basics | access control | authentication | software vulnerabilities | network attacks | secure coding | privacy | security policy
A22: CAS CS 240 | B22: CS | C22: Introduction to Machine Learning | D22: Computer Science | E22: Elective | F22: 200 | G22: 4 | I22: Fully synthetic course (not a real BU offering) | J22: Introduction to Machine Learning is an intermediate course in computer science. It covers supervised learning, linear regression, classification and model evaluation, and builds toward overfitting and regularization and clustering. Students work through programming assignments, with later units on neural networks and feature engineering. | K22: Explain the core ideas of supervised learning | Apply linear regression to solve standard problems | Analyze problems involving classification | Use model evaluation in practical exercises | Evaluate approaches to overfitting and regularization | Communicate findings about clustering | L22: supervised learning | linear regression | classification | model evaluation | overfitting and regularization | clustering | neural networks | feature engineering
A23: CAS CS 251 | B23: CS | C23: Mobile App Development | D23: Computer Science | E23: Elective | F23: 200 | G23: 4 | I23: Fully synthetic course (not a real BU offering) | J23: Mobile App Development is an intermediate course in computer science. It covers mobile platforms, user interface layout, event handling and local storage, and builds toward networking APIs and app lifecycle. Students work through programming assignments, with later units on testing on devices and app deployment. | K23: Explain the core ideas of mobile platforms | Apply user interface layout to solve standard problems | Analyze problems involving event handling | Use local storage in practical exercises | Evaluate approaches to networking APIs | Communicate findings about app lifecycle | L23: mobile platforms | user interface layout | event handling | local storage | networking APIs | app lifecycle | testing on devices | app deployment
A24: CAS CS 280 | B24: CS | C24: Human-Computer Interaction | D24: Computer Science | E24: Elective | F24: 200 | G24: 4 | I24: Fully synthetic course (not a real BU offering) | J24: Human-Computer Interaction is an intermediate course in computer science. It covers user-centered design, usability testing, prototyping and interaction design, and builds toward accessibility and cognitive models. Students work through programming assignments, with later units on visual design and user research. | K24: Explain the core ideas of user-centered design | Apply usability testing to solve standard problems | Analyze problems involving prototyping | Use interaction design in practical exercises | Evaluate approaches to accessibility | Communicate findings about cognitive models | L24: user-centered design | usability testing | prototyping | interaction design | accessibility | cognitive models | visual design | user research
... A33: CAS EC 102 | B33: EC | C33: Introductory Macroeconomic Analysis | D33: Economics | E33: Intro | F33: 100 | G33: 4 | I33: Code/title from provided BU workbook (public catalog); description synthetic | J33: Introductory Macroeconomic Analysis is an introductory course in economics. It covers GDP measurement, unemployment, inflation and aggregate demand and supply, and builds toward fiscal policy and monetary policy. Students work through data and policy exercises, with later units on economic growth and international trade basics. | K33: Explain the core ideas of GDP measurement | Apply unemployment to solve standard problems | Analyze problems involving inflation | Use aggregate demand and supply in practical exercises | Evaluate approaches to fiscal policy | Communicate findings about monetary policy | L33: GDP measurement | unemployment | inflation | aggregate demand and supply | fiscal policy | monetary policy | economic growth | international trade basics
A34: CAS EC 201 | B34: EC | C34: Intermediate Microeconomic Analysis | D34: Economics | E34: Core (200+ cap) | F34: 200 | G34: 4 | H34: Economics: max four 200+ level courses transferred after matriculation | I34: Code/title from provided BU workbook (public catalog); description synthetic | J34: Intermediate Microeconomic Analysis is an intermediate course in economics. It covers consumer theory, utility maximization, producer theory and cost minimization, and builds toward general equilibrium and welfare economics. Students work through data and policy exercises, with later units on game theory basics and market structures. | K34: Explain the core ideas of consumer theory | Apply utility maximization to solve standard problems | Analyze problems involving producer theory | Use cost minimization in practical exercises | Evaluate approaches to general equilibrium | Communicate findings about welfare economics | L34: consumer theory | utility maximization | producer theory | cost minimization | general equilibrium | welfare economics | game theory basics | market structures
A35: CAS EC 202 | B35: EC | C35: Intermediate Macroeconomic Analysis | D35: Economics | E35: Core (200+ cap) | F35: 200 | G35: 4 | H35: Economics: max four 200+ level courses transferred after matriculation | I35: Code/title from provided BU workbook (public catalog); description synthetic | J35: Intermediate Macroeconomic Analysis is an intermediate course in economics. It covers long-run growth models, IS-LM model, labor markets and consumption and saving, and builds toward investment and open-economy macroeconomics. Students work through data and policy exercises, with later units on monetary policy rules and business cycles. | K35: Explain the core ideas of long-run growth models | Apply IS-LM model to solve standard problems | Analyze problems involving labor markets | Use consumption and saving in practical exercises | Evaluate approaches to investment | Communicate findings about open-economy macroeconomics | L35: long-run growth models | IS-LM model | labor markets | consumption and saving | investment | open-economy macroeconomics | monetary policy rules | business cycles
A36: CAS EC 203 | B36: EC | C36: Empirical Economics 1 | D36: Economics | E36: Core (200+ cap) | F36: 200 | G36: 4 | H36: Economics: max four 200+ level courses transferred after matriculation | I36: Code/title from provided BU workbook (public catalog); description synthetic | J36: Empirical Economics 1 is an intermediate course in economics. It covers descriptive statistics, probability distributions, sampling and confidence intervals, and builds toward hypothesis testing and simple regression. Students work through data and policy exercises, with later units on statistical software and data interpretation. | K36: Explain the core ideas of descriptive statistics | Apply probability distributions to solve standard problems | Analyze problems involving sampling | Use confidence intervals in practical exercises | Evaluate approaches to hypothesis testing | Communicate findings about simple regression | L36: descriptive statistics | probability distributions | sampling | confidence intervals | hypothesis testing | simple regression | statistical software | data interpretation
A37: CAS EC 204 | B37: EC | C37: Empirical Economics 2 | D37: Economics | E37: Core (200+ cap) | F37: 200 | G37: 4 | H37: Economics: max four 200+ level courses transferred after matriculation | I37: Code/title from provided BU workbook (public catalog); description synthetic | J37: Empirical Economics 2 is an intermediate course in economics. It covers multiple regression, omitted variable bias, dummy variables and heteroskedasticity, and builds toward instrumental variables and panel data. Students work through data and policy exercises, with later units on causal inference and statistical software. | K37: Explain the core ideas of multiple regression | Apply omitted variable bias to solve standard problems | Analyze problems involving dummy variables | Use heteroskedasticity in practical exercises | Evaluate approaches to instrumental variables | Communicate findings about panel data | L37: multiple regression | omitted variable bias | dummy variables | heteroskedasticity | instrumental variables | panel data | causal inference | statistical software
A38: CAS EC 110 | B38: EC | C38: Economics of Everyday Life | D38: Economics | E38: Elective | F38: 100 | G38: 4 | I38: Fully synthetic course (not a real BU offering) | J38: Economics of Everyday Life is an introductory course in economics. It covers opportunity cost, incentives, personal finance and housing markets, and builds toward labor markets and health care choices. Students work through data and policy exercises, with later units on behavioral biases and public policy. | K38: Explain the core ideas of opportunity cost | Apply incentives to solve standard problems | Analyze problems involving personal finance | Use housing markets in practical exercises | Evaluate approaches to labor markets | Communicate findings about health care choices | L38: opportunity cost | incentives | personal finance | housing markets | labor markets | health care choices | behavioral biases | public policy
A39: CAS EC 220 | B39: EC | C39: Money and Banking | D39: Economics | E39: Elective (200+ cap) | F39: 200 | G39: 4 | H39: Economics: max four 200+ level courses transferred after matriculation | I39: Fully synthetic course (not a real BU offering) | J39: Money and Banking is an intermediate course in economics. It covers money supply, banking system, central banking and interest rates, and builds toward financial markets and monetary policy. Students work through data and policy exercises, with later units on financial crises and bank regulation. | K39: Explain the core ideas of money supply | Apply banking system to solve standard problems | Analyze problems involving central banking | Use interest rates in practical exercises | Evaluate approaches to financial markets | Communicate findings about monetary policy | L39: money supply | banking system | central banking | interest rates | financial markets | monetary policy | financial crises | bank regulation
A40: CAS EC 230 | B40: EC | C40: Public Finance | D40: Economics | E40: Elective (200+ cap) | F40: 200 | G40: 4 | H40: Economics: max four 200+ level courses transferred after matriculation | I40: Fully synthetic course (not a real BU offering) | J40: Public Finance is an intermediate course in economics. It covers public goods, externalities, taxation and tax incidence, and builds toward social insurance and government spending. Students work through data and policy exercises, with later units on cost-benefit analysis and fiscal federalism. | K40: Explain the core ideas of public goods | Apply externalities to solve standard problems | Analyze problems involving taxation | Use tax incidence in practical exercises | Evaluate approaches to social insurance | Communicate findings about government spending | L40: public goods | externalities | taxation | tax incidence | social insurance | government spending | cost-benefit analysis | fiscal federalism
A41: CAS EC 240 | B41: EC | C41: Labor Economics | D41: Economics | E41: Elective (200+ cap) | F41: 200 | G41: 4 | H41: Economics: max four 200+ level courses transferred after matriculation | I41: Fully synthetic course (not a real BU offering) | J41: Labor Economics is an intermediate course in economics. It covers labor supply, labor demand, wage determination and human capital, and builds toward discrimination and unions. Students work through data and policy exercises, with later units on minimum wage and unemployment. | K41: Explain the core ideas of labor supply | Apply labor demand to solve standard problems | Analyze problems involving wage determination | Use human capital in practical exercises | Evaluate approaches to discrimination | Communicate findings about unions | L41: labor supply | labor demand | wage determination | human capital | discrimination | unions | minimum wage | unemployment
A42: CAS EC 250 | B42: EC | C42: International Trade | D42: Economics | E42: Elective (200+ cap) | F42: 200 | G42: 4 | H42: Economics: max four 200+ level courses transferred after matriculation | I42: Fully synthetic course (not a real BU offering) | J42: International Trade is an intermediate course in economics. It covers comparative advantage, trade models, tariffs and quotas and trade agreements, and builds toward globalization and exchange rates. Students work through data and policy exercises, with later units on trade and inequality and multinational firms. | K42: Explain the core ideas of comparative advantage | Apply trade models to solve standard problems | Analyze problems involving tariffs and quotas | Use trade agreements in practical exercises | Evaluate approaches to globalization | Communicate findings about exchange rates | L42: comparative advantage | trade models | tariffs and quotas | trade agreements | globalization | exchange rates | trade and inequality | multinational firms
A43: CAS EC 260 | B43: EC | C43: Development Economics | D43: Economics | E43: Elective (200+ cap) | F43: 200 | G43: 4 | H43: Economics: max four 200+ level courses transferred after matriculation | I43: Fully synthetic course (not a real BU offering) | J43: Development Economics is an intermediate course in economics. It covers economic growth, poverty measurement, human capital and institutions, and builds toward microfinance and foreign aid. Students work through data and policy exercises, with later units on agriculture and randomized evaluations. | K43: Explain the core ideas of economic growth | Apply poverty measurement to solve standard problems | Analyze problems involving human capital | Use institutions in practical exercises | Evaluate approaches to microfinance | Communicate findings about foreign aid | L43: economic growth | poverty measurement | human capital | institutions | microfinance | foreign aid | agriculture | randomized evaluations
A44: CAS EC 270 | B44: EC | C44: Environmental Economics | D44: Economics | E44: Elective (200+ cap) | F44: 200 | G44: 4 | H44: Economics: max four 200+ level courses transferred after matriculation | I44: Fully synthetic course (not a real BU offering) | J44: Environmental Economics is an intermediate course in economics. It covers externalities, public goods, pollution regulation and carbon pricing, and builds toward cost-benefit analysis and natural resources. Students work through data and policy exercises, with later units on climate policy and valuation methods. | K44: Explain the core ideas of externalities | Apply public goods to solve standard problems | Analyze problems involving pollution regulation | Use carbon pricing in practical exercises | Evaluate approaches to cost-benefit analysis | Communicate findings about natural resources | L44: externalities | public goods | pollution regulation | carbon pricing | cost-benefit analysis | natural resources | climate policy | valuation methods
A45: CAS EC 280 | B45: EC | C45: Game Theory | D45: Economics | E45: Elective (200+ cap) | F45: 200 | G45: 4 | H45: Economics: max four 200+ level courses transferred after matriculation | I45: Fully synthetic course (not a real BU offering) | J45: Game Theory is an intermediate course in economics. It covers strategic games, Nash equilibrium, mixed strategies and sequential games, and builds toward repeated games and bargaining. Students work through data and policy exercises, with later units on auctions and mechanism design. | K45: Explain the core ideas of strategic games | Apply Nash equilibrium to solve standard problems | Analyze problems involving mixed strategies | Use sequential games in practical exercises | Evaluate approaches to repeated games | Communicate findings about bargaining | L45: strategic games | Nash equilibrium | mixed strategies | sequential games | repeated games | bargaining | auctions | mechanism design
A46: CAS EC 290 | B46: EC | C46: Economic History of the United States | D46: Economics | E46: Elective (200+ cap) | F46: 200 | G46: 4 | H46: Economics: max four 200+ level courses transferred after matriculation | I46: Fully synthetic course (not a real BU offering) | J46: Economic History of the United States is an intermediate course in economics. It covers colonial economy, industrialization, labor markets and the Great Depression, and builds toward financial crises and technological change. Students work through data and policy exercises, with later units on economic growth and government policy. | K46: Explain the core ideas of colonial economy | Apply industrialization to solve standard problems | Analyze problems involving labor markets | Use the Great Depression in practical exercises | Evaluate approaches to financial crises | Communicate findings about technological change | L46: colonial economy | industrialization | labor markets | the Great Depression | financial crises | technological change | economic growth | government policy
A47: CAS EC 305 | B47: EC | C47: Health Economics | D47: Economics | E47: Elective (200+ cap) | F47: 300 | G47: 4 | H47: Economics: max four 200+ level courses transferred after matriculation | I47: Fully synthetic course (not a real BU offering) | J47: Health Economics is an advanced course in economics. It covers demand for health care, health insurance, adverse selection and hospital markets, and builds toward pharmaceutical markets and health policy. Students work through data and policy exercises, with later units on cost-effectiveness and public health. | K47: Explain the core ideas of demand for health care | Apply health insurance to solve standard problems | Analyze problems involving adverse selection | Use hospital markets in practical exercises | Evaluate approaches to pharmaceutical markets | Communicate findings about health policy | L47: demand for health care | health insurance | adverse selection | hospital markets | pharmaceutical markets | health policy | cost-effectiveness | public health
A48: CAS EC 310 | B48: EC | C48: Urban Economics | D48: Economics | E48: Elective (200+ cap) | F48: 300 | G48: 4 | H48: Economics: max four 200+ level courses transferred after matriculation | I48: Fully synthetic course (not a real BU offering) | J48: Urban Economics is an advanced course in economics. It covers city formation, land use, housing markets and transportation, and builds toward local public goods and segregation. Students work through data and policy exercises, with later units on urban policy and agglomeration. | K48: Explain the core ideas of city formation | Apply land use to solve standard problems | Analyze problems involving housing markets | Use transportation in practical exercises | Evaluate approaches to local public goods | Communicate findings about segregation | L48: city formation | land use | housing markets | transportation | local public goods | segregation | urban policy | agglomeration
A49: CAS EC 315 | B49: EC | C49: Behavioral Economics | D49: Economics | E49: Elective (200+ cap) | F49: 300 | G49: 4 | H49: Economics: max four 200+ level courses transferred after matriculation | I49: Fully synthetic course (not a real BU offering) | J49: Behavioral Economics is an advanced course in economics. It covers bounded rationality, prospect theory, time inconsistency and social preferences, and builds toward heuristics and biases and nudges. Students work through data and policy exercises, with later units on experiments and behavioral finance. | K49: Explain the core ideas of bounded rationality | Apply prospect theory to solve standard problems | Analyze problems involving time inconsistency | Use social preferences in practical exercises | Evaluate approaches to heuristics and biases | Communicate findings about nudges | L49: bounded rationality | prospect theory | time inconsistency | social preferences | heuristics and biases | nudges | experiments | behavioral finance
A50: CAS EC 320 | B50: EC | C50: Industrial Organization | D50: Economics | E50: Elective (200+ cap) | F50: 300 | G50: 4 | H50: Economics: max four 200+ level courses transferred after matriculation | I50: Fully synthetic course (not a real BU offering) | J50: Industrial Organization is an advanced course in economics. It covers market structures, monopoly, oligopoly and price discrimination, and builds toward product differentiation and entry and exit. Students work through data and policy exercises, with later units on antitrust and vertical integration. | K50: Explain the core ideas of market structures | Apply monopoly to solve standard problems | Analyze problems involving oligopoly | Use price discrimination in practical exercises | Evaluate approaches to product differentiation | Communicate findings about entry and exit | L50: market structures | monopoly | oligopoly | price discrimination | product differentiation | entry and exit | antitrust | vertical integration
... A59: CAS EC 365 | B59: EC | C59: Time Series Forecasting | D59: Economics | E59: Elective (200+ cap) | F59: 300 | G59: 4 | H59: Economics: max four 200+ level courses transferred after matriculation | I59: Fully synthetic course (not a real BU offering) | J59: Time Series Forecasting is an advanced course in economics. It covers time series data, autocorrelation, ARIMA models and trend and seasonality, and builds toward forecasting evaluation and volatility models. Students work through data and policy exercises, with later units on vector autoregression and statistical software. | K59: Explain the core ideas of time series data | Apply autocorrelation to solve standard problems | Analyze problems involving ARIMA models | Use trend and seasonality in practical exercises | Evaluate approaches to forecasting evaluation | Communicate findings about volatility models | L59: time series data | autocorrelation | ARIMA models | trend and seasonality | forecasting evaluation | volatility models | vector autoregression | statistical software
A60: CAS PS 101 | B60: PS | C60: General Psychology | D60: Psychology | E60: Prerequisite | F60: 100 | G60: 4 | I60: Code/title from provided BU workbook (public catalog); description synthetic | J60: General Psychology is an introductory course in psychology. It covers history of psychology, research methods, biological bases of behavior and sensation and perception, and builds toward learning and memory. Students work through readings and short research reports, with later units on development and psychological disorders. | K60: Explain the core ideas of history of psychology | Apply research methods to solve standard problems | Analyze problems involving biological bases of behavior | Use sensation and perception in practical exercises | Evaluate approaches to learning | Communicate findings about memory | L60: history of psychology | research methods | biological bases of behavior | sensation and perception | learning | memory | development | psychological disorders
A61: CAS PS 211 | B61: PS | C61: Experimental Design in Psychology | D61: Psychology | E61: Design & Statistics | F61: 200 | G61: 4 | I61: Code/title from provided BU workbook (public catalog); description synthetic | J61: Experimental Design in Psychology is an intermediate course in psychology. It covers scientific method, research ethics, experimental design and descriptive statistics, and builds toward hypothesis testing and t-tests and ANOVA. Students work through readings and short research reports, with later units on correlation and regression and APA-style reporting. | K61: Explain the core ideas of scientific method | Apply research ethics to solve standard problems | Analyze problems involving experimental design | Use descriptive statistics in practical exercises | Evaluate approaches to hypothesis testing | Communicate findings about t-tests and ANOVA | L61: scientific method | research ethics | experimental design | descriptive statistics | hypothesis testing | t-tests and ANOVA | correlation and regression | APA-style reporting
A62: CAS PS 231 | B62: PS | C62: Physiological Psychology | D62: Psychology | E62: Required principal | F62: 200 | G62: 4 | I62: Code/title from provided BU workbook (public catalog); description synthetic | J62: Physiological Psychology is an intermediate course in psychology. It covers neurons and synapses, neurotransmitters, brain anatomy and sensory systems, and builds toward motor control and sleep. Students work through readings and short research reports, with later units on emotion and the brain and neuroplasticity. | K62: Explain the core ideas of neurons and synapses | Apply neurotransmitters to solve standard problems | Analyze problems involving brain anatomy | Use sensory systems in practical exercises | Evaluate approaches to motor control | Communicate findings about sleep | L62: neurons and synapses | neurotransmitters | brain anatomy | sensory systems | motor control | sleep | emotion and the brain | neuroplasticity
A63: CAS PS 222 | B63: PS | C63: Perception and Behavior | D63: Psychology | E63: Group A | F63: 200 | G63: 4 | I63: Code/title from provided BU workbook (public catalog); description synthetic | J63: Perception and Behavior is an intermediate course in psychology. It covers psychophysics, visual system, color perception and depth perception, and builds toward auditory perception and attention. Students work through readings and short research reports, with later units on object recognition and multisensory integration. | K63: Explain the core ideas of psychophysics | Apply visual system to solve standard problems | Analyze problems involving color perception | Use depth perception in practical exercises | Evaluate approaches to auditory perception | Communicate findings about attention | L63: psychophysics | visual system | color perception | depth perception | auditory perception | attention | object recognition | multisensory integration
A64: CAS PS 336 | B64: PS | C64: Introduction to Cognitive Psychology | D64: Psychology | E64: Group A | F64: 300 | G64: 4 | I64: Code/title from provided BU workbook (public catalog); description synthetic | J64: Introduction to Cognitive Psychology is an advanced course in psychology. It covers attention, working memory, long-term memory and categorization, and builds toward language and problem solving. Students work through readings and short research reports, with later units on decision making and reasoning. | K64: Explain the core ideas of attention | Apply working memory to solve standard problems | Analyze problems involving long-term memory | Use categorization in practical exercises | Evaluate approaches to language | Communicate findings about problem solving | L64: attention | working memory | long-term memory | categorization | language | problem solving | decision making | reasoning
A65: CAS PS 241 | B65: PS | C65: Developmental Psychology | D65: Psychology | E65: Group B | F65: 200 | G65: 4 | I65: Code/title from provided BU workbook (public catalog); description synthetic | J65: Developmental Psychology is an intermediate course in psychology. It covers prenatal development, infancy, cognitive development and language development, and builds toward social development and adolescence. Students work through readings and short research reports, with later units on attachment and developmental research methods. | K65: Explain the core ideas of prenatal development | Apply infancy to solve standard problems | Analyze problems involving cognitive development | Use language development in practical exercises | Evaluate approaches to social development | Communicate findings about adolescence | L65: prenatal development | infancy | cognitive development | language development | social development | adolescence | attachment | developmental research methods
A66: CAS PS 251 | B66: PS | C66: Psychology of Personality: Theories and Application | D66: Psychology | E66: Group B | F66: 200 | G66: 4 | I66: Code/title from provided BU workbook (public catalog); description synthetic | J66: Psychology of Personality: Theories and Application is an intermediate course in psychology. It covers psychodynamic theory, trait theory, humanistic theory and social-cognitive theory, and builds toward personality assessment and biological bases of personality. Students work through readings and short research reports, with later units on culture and personality and personality stability. | K66: Explain the core ideas of psychodynamic theory | Apply trait theory to solve standard problems | Analyze problems involving humanistic theory | Use social-cognitive theory in practical exercises | Evaluate approaches to personality assessment | Communicate findings about biological bases of personality | L66: psychodynamic theory | trait theory | humanistic theory | social-cognitive theory | personality assessment | biological bases of personality | culture and personality | personality stability
A67: CAS PS 261 | B67: PS | C67: Social Psychology | D67: Psychology | E67: Group B | F67: 200 | G67: 4 | I67: Code/title from provided BU workbook (public catalog); description synthetic | J67: Social Psychology is an intermediate course in psychology. It covers social cognition, attitudes, persuasion and conformity, and builds toward group behavior and prejudice. Students work through readings and short research reports, with later units on interpersonal attraction and prosocial behavior. | K67: Explain the core ideas of social cognition | Apply attitudes to solve standard problems | Analyze problems involving persuasion | Use conformity in practical exercises | Evaluate approaches to group behavior | Communicate findings about prejudice | L67: social cognition | attitudes | persuasion | conformity | group behavior | prejudice | interpersonal attraction | prosocial behavior
A68: CAS PS 371 | B68: PS | C68: Psychopathology | D68: Psychology | E68: Group B | F68: 300 | G68: 4 | I68: Code/title from provided BU workbook (public catalog); description synthetic | J68: Psychopathology is an advanced course in psychology. It covers diagnostic classification, anxiety disorders, mood disorders and schizophrenia, and builds toward personality disorders and substance use disorders. Students work through readings and short research reports, with later units on etiology models and evidence-based treatment. | K68: Explain the core ideas of diagnostic classification | Apply anxiety disorders to solve standard problems | Analyze problems involving mood disorders | Use schizophrenia in practical exercises | Evaluate approaches to personality disorders | Communicate findings about substance use disorders | L68: diagnostic classification | anxiety disorders | mood disorders | schizophrenia | personality disorders | substance use disorders | etiology models | evidence-based treatment
A69: CAS PS 110 | B69: PS | C69: Psychology of Everyday Life | D69: Psychology | E69: Elective | F69: 100 | G69: 4 | I69: Fully synthetic course (not a real BU offering) | J69: Psychology of Everyday Life is an introductory course in psychology. It covers stress and coping, habits, motivation and relationships, and builds toward sleep and emotion. Students work through readings and short research reports, with later units on decision making and well-being. | K69: Explain the core ideas of stress and coping | Apply habits to solve standard problems | Analyze problems involving motivation | Use relationships in practical exercises | Evaluate approaches to sleep | Communicate findings about emotion | L69: stress and coping | habits | motivation | relationships | sleep | emotion | decision making | well-being
A70: CAS PS 205 | B70: PS | C70: Statistics for Psychology | D70: Psychology | E70: Elective | F70: 200 | G70: 4 | I70: Fully synthetic course (not a real BU offering) | J70: Statistics for Psychology is an intermediate course in psychology. It covers descriptive statistics, probability, sampling distributions and hypothesis testing, and builds toward t-tests and ANOVA and correlation and regression. Students work through readings and short research reports, with later units on nonparametric tests and statistical software. | K70: Explain the core ideas of descriptive statistics | Apply probability to solve standard problems | Analyze problems involving sampling distributions | Use hypothesis testing in practical exercises | Evaluate approaches to t-tests and ANOVA | Communicate findings about correlation and regression | L70: descriptive statistics | probability | sampling distributions | hypothesis testing | t-tests and ANOVA | correlation and regression | nonparametric tests | statistical software
A71: CAS PS 225 | B71: PS | C71: Learning and Behavior | D71: Psychology | E71: Elective | F71: 200 | G71: 4 | I71: Fully synthetic course (not a real BU offering) | J71: Learning and Behavior is an intermediate course in psychology. It covers classical conditioning, operant conditioning, reinforcement schedules and observational learning, and builds toward extinction and behavior modification. Students work through readings and short research reports, with later units on animal learning and learning theories. | K71: Explain the core ideas of classical conditioning | Apply operant conditioning to solve standard problems | Analyze problems involving reinforcement schedules | Use observational learning in practical exercises | Evaluate approaches to extinction | Communicate findings about behavior modification | L71: classical conditioning | operant conditioning | reinforcement schedules | observational learning | extinction | behavior modification | animal learning | learning theories
... A91: CAS BI 108 | B91: BI | C91: Biology 2 | D91: Biology | E91: Intro | F91: 100 | G91: 4 | I91: Code/title from provided BU workbook (public catalog); description synthetic | J91: Biology 2 is an introductory course in biology. It covers cell metabolism, photosynthesis, cellular respiration and molecular genetics, and builds toward gene expression and cell division. Students work through weekly laboratory sessions, with later units on physiology and laboratory techniques. | K91: Explain the core ideas of cell metabolism | Apply photosynthesis to solve standard problems | Analyze problems involving cellular respiration | Use molecular genetics in practical exercises | Evaluate approaches to gene expression | Communicate findings about cell division | L91: cell metabolism | photosynthesis | cellular respiration | molecular genetics | gene expression | cell division | physiology | laboratory techniques
A92: CAS BI 203 | B92: BI | C92: Cell Biology | D92: Biology | E92: Core | F92: 200 | G92: 4 | H92: Biology: at least five BI courses beyond BI 107/108 must be taken at BU | I92: Code/title from provided BU workbook (public catalog); description synthetic | J92: Cell Biology is an intermediate course in biology. It covers membrane structure, protein trafficking, cytoskeleton and cell signaling, and builds toward cell cycle and organelles. Students work through weekly laboratory sessions, with later units on cell communication and microscopy. | K92: Explain the core ideas of membrane structure | Apply protein trafficking to solve standard problems | Analyze problems involving cytoskeleton | Use cell signaling in practical exercises | Evaluate approaches to cell cycle | Communicate findings about organelles | L92: membrane structure | protein trafficking | cytoskeleton | cell signaling | cell cycle | organelles | cell communication | microscopy
A93: CAS BI 206 | B93: BI | C93: Genetics | D93: Biology | E93: Core | F93: 200 | G93: 4 | H93: Biology: at least five BI courses beyond BI 107/108 must be taken at BU | I93: Code/title from provided BU workbook (public catalog); description synthetic | J93: Genetics is an intermediate course in biology. It covers Mendelian genetics, chromosomes, DNA replication and gene expression, and builds toward mutation and population genetics. Students work through weekly laboratory sessions, with later units on genetic mapping and genomics. | K93: Explain the core ideas of Mendelian genetics | Apply chromosomes to solve standard problems | Analyze problems involving DNA replication | Use gene expression in practical exercises | Evaluate approaches to mutation | Communicate findings about population genetics | L93: Mendelian genetics | chromosomes | DNA replication | gene expression | mutation | population genetics | genetic mapping | genomics
A94: CAS CH 101 | B94: CH | C94: General Chemistry 1 | D94: Biology | E94: Supporting (Chemistry) | F94: 100 | G94: 4 | I94: Code/title from provided BU workbook (public catalog); description synthetic | J94: General Chemistry 1 is an introductory course in biology. It covers atomic structure, periodic trends, chemical bonding and stoichiometry, and builds toward gas laws and thermochemistry. Students work through weekly laboratory sessions, with later units on solutions and laboratory safety. | K94: Explain the core ideas of atomic structure | Apply periodic trends to solve standard problems | Analyze problems involving chemical bonding | Use stoichiometry in practical exercises | Evaluate approaches to gas laws | Communicate findings about thermochemistry | L94: atomic structure | periodic trends | chemical bonding | stoichiometry | gas laws | thermochemistry | solutions | laboratory safety
A95: CAS CH 102 | B95: CH | C95: General Chemistry 2 | D95: Biology | E95: Supporting (Chemistry) | F95: 100 | G95: 4 | I95: Code/title from provided BU workbook (public catalog); description synthetic | J95: General Chemistry 2 is an introductory course in biology. It covers chemical kinetics, chemical equilibrium, acids and bases and buffers, and builds toward thermodynamics and electrochemistry. Students work through weekly laboratory sessions, with later units on nuclear chemistry and laboratory techniques. | K95: Explain the core ideas of chemical kinetics | Apply chemical equilibrium to solve standard problems | Analyze problems involving acids and bases | Use buffers in practical exercises | Evaluate approaches to thermodynamics | Communicate findings about electrochemistry | L95: chemical kinetics | chemical equilibrium | acids and bases | buffers | thermodynamics | electrochemistry | nuclear chemistry | laboratory techniques
A96: CAS CH 203 | B96: CH | C96: Organic Chemistry 1 | D96: Biology | E96: Supporting (Chemistry) | F96: 200 | G96: 4 | I96: Code/title from provided BU workbook (public catalog); description synthetic | J96: Organic Chemistry 1 is an intermediate course in biology. It covers molecular structure, stereochemistry, nomenclature and reaction mechanisms, and builds toward substitution reactions and elimination reactions. Students work through weekly laboratory sessions, with later units on alkenes and alkynes and spectroscopy. | K96: Explain the core ideas of molecular structure | Apply stereochemistry to solve standard problems | Analyze problems involving nomenclature | Use reaction mechanisms in practical exercises | Evaluate approaches to substitution reactions | Communicate findings about elimination reactions | L96: molecular structure | stereochemistry | nomenclature | reaction mechanisms | substitution reactions | elimination reactions | alkenes and alkynes | spectroscopy
A97: CAS CH 204 | B97: CH | C97: Organic Chemistry 2 | D97: Biology | E97: Supporting (Chemistry) | F97: 200 | G97: 4 | I97: Code/title from provided BU workbook (public catalog); description synthetic | J97: Organic Chemistry 2 is an intermediate course in biology. It covers aromatic compounds, carbonyl chemistry, alcohols and ethers and amines, and builds toward reaction mechanisms and synthesis planning. Students work through weekly laboratory sessions, with later units on spectroscopy and biomolecules. | K97: Explain the core ideas of aromatic compounds | Apply carbonyl chemistry to solve standard problems | Analyze problems involving alcohols and ethers | Use amines in practical exercises | Evaluate approaches to reaction mechanisms | Communicate findings about synthesis planning | L97: aromatic compounds | carbonyl chemistry | alcohols and ethers | amines | reaction mechanisms | synthesis planning | spectroscopy | biomolecules
A98: CAS BI 105 | B98: BI | C98: Human Biology | D98: Biology | E98: Elective | F98: 100 | G98: 4 | I98: Fully synthetic course (not a real BU offering) | J98: Human Biology is an introductory course in biology. It covers cell structure, human organ systems, nutrition and genetics and heredity, and builds toward infectious disease and reproduction. Students work through weekly laboratory sessions, with later units on human evolution and health and society. | K98: Explain the core ideas of cell structure | Apply human organ systems to solve standard problems | Analyze problems involving nutrition | Use genetics and heredity in practical exercises | Evaluate approaches to infectious disease | Communicate findings about reproduction | L98: cell structure | human organ systems | nutrition | genetics and heredity | infectious disease | reproduction | human evolution | health and society
A99: CAS BI 110 | B99: BI | C99: Environmental Science | D99: Biology | E99: Elective | F99: 100 | G99: 4 | H99: Biology: at least five BI courses beyond BI 107/108 must be taken at BU | I99: Fully synthetic course (not a real BU offering) | J99: Environmental Science is an introductory course in biology. It covers ecosystems, biodiversity, climate change and pollution, and builds toward energy resources and water resources. Students work through weekly laboratory sessions, with later units on sustainability and environmental policy. | K99: Explain the core ideas of ecosystems | Apply biodiversity to solve standard problems | Analyze problems involving climate change | Use pollution in practical exercises | Evaluate approaches to energy resources | Communicate findings about water resources | L99: ecosystems | biodiversity | climate change | pollution | energy resources | water resources | sustainability | environmental policy
A100: CAS BI 114 | B100: BI | C100: Human Anatomy and Physiology 1 | D100: Biology | E100: Elective | F100: 100 | G100: 4 | H100: Biology: at least five BI courses beyond BI 107/108 must be taken at BU | I100: Fully synthetic course (not a real BU offering) | J100: Human Anatomy and Physiology 1 is an introductory course in biology. It covers tissues, skeletal system, muscular system and nervous system, and builds toward sensory systems and integumentary system. Students work through weekly laboratory sessions, with later units on homeostasis and laboratory dissection. | K100: Explain the core ideas of tissues | Apply skeletal system to solve standard problems | Analyze problems involving muscular system | Use nervous system in practical exercises | Evaluate approaches to sensory systems | Communicate findings about integumentary system | L100: tissues | skeletal system | muscular system | nervous system | sensory systems | integumentary system | homeostasis | laboratory dissection
A101: CAS BI 116 | B101: BI | C101: Human Anatomy and Physiology 2 | D101: Biology | E101: Elective | F101: 100 | G101: 4 | H101: Biology: at least five BI courses beyond BI 107/108 must be taken at BU | I101: Fully synthetic course (not a real BU offering) | J101: Human Anatomy and Physiology 2 is an introductory course in biology. It covers cardiovascular system, respiratory system, digestive system and urinary system, and builds toward endocrine system and reproductive system. Students work through weekly laboratory sessions, with later units on immune system and homeostasis. | K101: Explain the core ideas of cardiovascular system | Apply respiratory system to solve standard problems | Analyze problems involving digestive system | Use urinary system in practical exercises | Evaluate approaches to endocrine system | Communicate findings about reproductive system | L101: cardiovascular system | respiratory system | digestive system | urinary system | endocrine system | reproductive system | immune system | homeostasis
A102: CAS BI 210 | B102: BI | C102: Microbiology | D102: Biology | E102: Elective | F102: 200 | G102: 4 | H102: Biology: at least five BI courses beyond BI 107/108 must be taken at BU | I102: Fully synthetic course (not a real BU offering) | J102: Microbiology is an intermediate course in biology. It covers microbial cell structure, microbial growth, microbial metabolism and microbial genetics, and builds toward viruses and host-pathogen interactions. Students work through weekly laboratory sessions, with later units on immunology basics and aseptic technique. | K102: Explain the core ideas of microbial cell structure | Apply microbial growth to solve standard problems | Analyze problems involving microbial metabolism | Use microbial genetics in practical exercises | Evaluate approaches to viruses | Communicate findings about host-pathogen interactions | L102: microbial cell structure | microbial growth | microbial metabolism | microbial genetics | viruses | host-pathogen interactions | immunology basics | aseptic technique
A103: CAS BI 225 | B103: BI | C103: Ecology | D103: Biology | E103: Elective | F103: 200 | G103: 4 | H103: Biology: at least five BI courses beyond BI 107/108 must be taken at BU | I103: Fully synthetic course (not a real BU offering) | J103: Ecology is an intermediate course in biology. It covers population ecology, community ecology, ecosystems and biodiversity, and builds toward species interactions and nutrient cycles. Students work through weekly laboratory sessions, with later units on field methods and conservation. | K103: Explain the core ideas of population ecology | Apply community ecology to solve standard problems | Analyze problems involving ecosystems | Use biodiversity in practical exercises | Evaluate approaches to species interactions | Communicate findings about nutrient cycles | L103: population ecology | community ecology | ecosystems | biodiversity | species interactions | nutrient cycles | field methods | conservation
A104: CAS BI 230 | B104: BI | C104: Evolution | D104: Biology | E104: Elective | F104: 200 | G104: 4 | H104: Biology: at least five BI courses beyond BI 107/108 must be taken at BU | I104: Fully synthetic course (not a real BU offering) | J104: Evolution is an intermediate course in biology. It covers natural selection, population genetics, speciation and phylogenetics, and builds toward adaptation and molecular evolution. Students work through weekly laboratory sessions, with later units on human evolution and evolutionary developmental biology. | K104: Explain the core ideas of natural selection | Apply population genetics to solve standard problems | Analyze problems involving speciation | Use phylogenetics in practical exercises | Evaluate approaches to adaptation | Communicate findings about molecular evolution | L104: natural selection | population genetics | speciation | phylogenetics | adaptation | molecular evolution | human evolution | evolutionary developmental biology
A105: CAS BI 260 | B105: BI | C105: Marine Biology | D105: Biology | E105: Elective | F105: 200 | G105: 4 | H105: Biology: at least five BI courses beyond BI 107/108 must be taken at BU | I105: Fully synthetic course (not a real BU offering) | J105: Marine Biology is an intermediate course in biology. It covers ocean environments, marine biodiversity, plankton and coral reefs, and builds toward marine ecosystems and marine conservation. Students work through weekly laboratory sessions, with later units on field methods and fisheries. | K105: Explain the core ideas of ocean environments | Apply marine biodiversity to solve standard problems | Analyze problems involving plankton | Use coral reefs in practical exercises | Evaluate approaches to marine ecosystems | Communicate findings about marine conservation | L105: ocean environments | marine biodiversity | plankton | coral reefs | marine ecosystems | marine conservation | field methods | fisheries
A106: CAS BI 302 | B106: BI | C106: Vertebrate Zoology | D106: Biology | E106: Elective | F106: 300 | G106: 4 | H106: Biology: at least five BI courses beyond BI 107/108 must be taken at BU | I106: Fully synthetic course (not a real BU offering) | J106: Vertebrate Zoology is an advanced course in biology. It covers vertebrate evolution, comparative anatomy, fishes and amphibians, and builds toward reptiles and birds. Students work through weekly laboratory sessions, with later units on mammals and phylogenetics. | K106: Explain the core ideas of vertebrate evolution | Apply comparative anatomy to solve standard problems | Analyze problems involving fishes | Use amphibians in practical exercises | Evaluate approaches to reptiles | Communicate findings about birds | L106: vertebrate evolution | comparative anatomy | fishes | amphibians | reptiles | birds | mammals | phylogenetics
A107: CAS BI 303 | B107: BI | C107: Plant Biology | D107: Biology | E107: Elective | F107: 300 | G107: 4 | H107: Biology: at least five BI courses beyond BI 107/108 must be taken at BU | I107: Fully synthetic course (not a real BU offering) | J107: Plant Biology is an advanced course in biology. It covers plant structure, photosynthesis, plant hormones and plant reproduction, and builds toward plant diversity and plant ecology. Students work through weekly laboratory sessions, with later units on plant genetics and laboratory techniques. | K107: Explain the core ideas of plant structure | Apply photosynthesis to solve standard problems | Analyze problems involving plant hormones | Use plant reproduction in practical exercises | Evaluate approaches to plant diversity | Communicate findings about plant ecology | L107: plant structure | photosynthesis | plant hormones | plant reproduction | plant diversity | plant ecology | plant genetics | laboratory techniques
A108: CAS BI 315 | B108: BI | C108: Neurobiology | D108: Biology | E108: Elective | F108: 300 | G108: 4 | H108: Biology: at least five BI courses beyond BI 107/108 must be taken at BU | I108: Fully synthetic course (not a real BU offering) | J108: Neurobiology is an advanced course in biology. It covers neurons and synapses, action potentials, neurotransmitters and sensory systems, and builds toward motor control and neural development. Students work through weekly laboratory sessions, with later units on learning and memory and neuroplasticity. | K108: Explain the core ideas of neurons and synapses | Apply action potentials to solve standard problems | Analyze problems involving neurotransmitters | Use sensory systems in practical exercises | Evaluate approaches to motor control | Communicate findings about neural development | L108: neurons and synapses | action potentials | neurotransmitters | sensory systems | motor control | neural development | learning and memory | neuroplasticity
A109: CAS BI 325 | B109: BI | C109: Immunology | D109: Biology | E109: Elective | F109: 300 | G109: 4 | H109: Biology: at least five BI courses beyond BI 107/108 must be taken at BU | I109: Fully synthetic course (not a real BU offering) | J109: Immunology is an advanced course in biology. It covers innate immunity, adaptive immunity, antibodies and T cells, and builds toward antigen presentation and immunological memory. Students work through weekly laboratory sessions, with later units on vaccines and immune disorders. | K109: Explain the core ideas of innate immunity | Apply adaptive immunity to solve standard problems | Analyze problems involving antibodies | Use T cells in practical exercises | Evaluate approaches to antigen presentation | Communicate findings about immunological memory | L109: innate immunity | adaptive immunity | antibodies | T cells | antigen presentation | immunological memory | vaccines | immune disorders
A110: CAS BI 330 | B110: BI | C110: Developmental Biology | D110: Biology | E110: Elective | F110: 300 | G110: 4 | H110: Biology: at least five BI courses beyond BI 107/108 must be taken at BU | I110: Fully synthetic course (not a real BU offering) | J110: Developmental Biology is an advanced course in biology. It covers fertilization, embryonic development, cell differentiation and pattern formation, and builds toward organogenesis and stem cells. Students work through weekly laboratory sessions, with later units on gene regulation in development and evolutionary developmental biology. | K110: Explain the core ideas of fertilization | Apply embryonic development to solve standard problems | Analyze problems involving cell differentiation | Use pattern formation in practical exercises | Evaluate approaches to organogenesis | Communicate findings about stem cells | L110: fertilization | embryonic development | cell differentiation | pattern formation | organogenesis | stem cells | gene regulation in development | evolutionary developmental biology
... A115: CAS BI 380 | B115: BI | C115: Virology | D115: Biology | E115: Elective | F115: 300 | G115: 4 | H115: Biology: at least five BI courses beyond BI 107/108 must be taken at BU | I115: Fully synthetic course (not a real BU offering) | J115: Virology is an advanced course in biology. It covers virus structure, viral replication, viral genetics and host-pathogen interactions, and builds toward viral evolution and vaccines. Students work through weekly laboratory sessions, with later units on antiviral drugs and emerging viruses. | K115: Explain the core ideas of virus structure | Apply viral replication to solve standard problems | Analyze problems involving viral genetics | Use host-pathogen interactions in practical exercises | Evaluate approaches to viral evolution | Communicate findings about vaccines | L115: virus structure | viral replication | viral genetics | host-pathogen interactions | viral evolution | vaccines | antiviral drugs | emerging viruses
A116: CAS CH 110 | B116: CH | C116: Chemistry for Health Sciences | D116: Biology | E116: Elective | F116: 100 | G116: 4 | I116: Fully synthetic course (not a real BU offering) | J116: Chemistry for Health Sciences is an introductory course in biology. It covers atomic structure, chemical bonding, solutions and acids and bases, and builds toward organic functional groups and biomolecules. Students work through weekly laboratory sessions, with later units on metabolism and laboratory safety. | K116: Explain the core ideas of atomic structure | Apply chemical bonding to solve standard problems | Analyze problems involving solutions | Use acids and bases in practical exercises | Evaluate approaches to organic functional groups | Communicate findings about biomolecules | L116: atomic structure | chemical bonding | solutions | acids and bases | organic functional groups | biomolecules | metabolism | laboratory safety
A117: CAS CH 211 | B117: CH | C117: Analytical Chemistry | D117: Biology | E117: Elective | F117: 200 | G117: 4 | I117: Fully synthetic course (not a real BU offering) | J117: Analytical Chemistry is an intermediate course in biology. It covers statistics for chemistry, titrations, chemical equilibrium and spectroscopy, and builds toward chromatography and electrochemistry. Students work through weekly laboratory sessions, with later units on quality control and laboratory techniques. | K117: Explain the core ideas of statistics for chemistry | Apply titrations to solve standard problems | Analyze problems involving chemical equilibrium | Use spectroscopy in practical exercises | Evaluate approaches to chromatography | Communicate findings about electrochemistry | L117: statistics for chemistry | titrations | chemical equilibrium | spectroscopy | chromatography | electrochemistry | quality control | laboratory techniques
A118: CAS CH 373 | B118: CH | C118: Biochemistry 1 | D118: Biology | E118: Elective | F118: 300 | G118: 4 | I118: Fully synthetic course (not a real BU offering) | J118: Biochemistry 1 is an advanced course in biology. It covers amino acids and proteins, enzyme kinetics, carbohydrates and lipids and membranes, and builds toward metabolism and bioenergetics. Students work through weekly laboratory sessions, with later units on nucleic acids and laboratory techniques. | K118: Explain the core ideas of amino acids and proteins | Apply enzyme kinetics to solve standard problems | Analyze problems involving carbohydrates | Use lipids and membranes in practical exercises | Evaluate approaches to metabolism | Communicate findings about bioenergetics | L118: amino acids and proteins | enzyme kinetics | carbohydrates | lipids and membranes | metabolism | bioenergetics | nucleic acids | laboratory techniques
A119: CAS CH 374 | B119: CH | C119: Biochemistry 2 | D119: Biology | E119: Elective | F119: 300 | G119: 4 | I119: Fully synthetic course (not a real BU offering) | J119: Biochemistry 2 is an advanced course in biology. It covers metabolism, bioenergetics, lipid metabolism and nitrogen metabolism, and builds toward signal transduction and gene expression. Students work through weekly laboratory sessions, with later units on metabolic regulation and biomolecules. | K119: Explain the core ideas of metabolism | Apply bioenergetics to solve standard problems | Analyze problems involving lipid metabolism | Use nitrogen metabolism in practical exercises | Evaluate approaches to signal transduction | Communicate findings about gene expression | L119: metabolism | bioenergetics | lipid metabolism | nitrogen metabolism | signal transduction | gene expression | metabolic regulation | biomolecules
A120: CAS CH 301 | B120: CH | C120: Physical Chemistry for Life Sciences | D120: Biology | E120: Elective | F120: 300 | G120: 4 | I120: Fully synthetic course (not a real BU offering) | J120: Physical Chemistry for Life Sciences is an advanced course in biology. It covers thermodynamics, chemical kinetics, quantum chemistry basics and spectroscopy, and builds toward statistical mechanics and biomolecular structure. Students work through weekly laboratory sessions, with later units on transport processes and mathematical modeling. | K120: Explain the core ideas of thermodynamics | Apply chemical kinetics to solve standard problems | Analyze problems involving quantum chemistry basics | Use spectroscopy in practical exercises | Evaluate approaches to statistical mechanics | Communicate findings about biomolecular structure | L120: thermodynamics | chemical kinetics | quantum chemistry basics | spectroscopy | statistical mechanics | biomolecular structure | transport processes | mathematical modeling
A121: CAS BI 340 | B121: BI | C121: Endocrinology | D121: Biology | E121: Elective | F121: 300 | G121: 4 | H121: Biology: at least five BI courses beyond BI 107/108 must be taken at BU | I121: Fully synthetic course (not a real BU offering) | J121: Endocrinology is an advanced course in biology. It covers endocrine system, hormone signaling, pituitary and hypothalamus and thyroid, and builds toward metabolism and reproductive hormones. Students work through weekly laboratory sessions, with later units on stress hormones and endocrine disorders. | K121: Explain the core ideas of endocrine system | Apply hormone signaling to solve standard problems | Analyze problems involving pituitary and hypothalamus | Use thyroid in practical exercises | Evaluate approaches to metabolism | Communicate findings about reproductive hormones | L121: endocrine system | hormone signaling | pituitary and hypothalamus | thyroid | metabolism | reproductive hormones | stress hormones | endocrine disorders
A122: CAS MA 123 | B122: MA | C122: Calculus I | D122: Mathematics | E122: Lower division | F122: 100 | G122: 4 | I122: Code/title from provided BU workbook (public catalog); description synthetic | J122: Calculus I is an introductory course in mathematics. It covers functions, limits, continuity and derivatives, and builds toward differentiation rules and applications of derivatives. Students work through problem sets and proofs, with later units on optimization and introduction to integrals. | K122: Explain the core ideas of functions | Apply limits to solve standard problems | Analyze problems involving continuity | Use derivatives in practical exercises | Evaluate approaches to differentiation rules | Communicate findings about applications of derivatives | L122: functions | limits | continuity | derivatives | differentiation rules | applications of derivatives | optimization | introduction to integrals
A123: CAS MA 124 | B123: MA | C123: Calculus II | D123: Mathematics | E123: Lower division | F123: 100 | G123: 4 | I123: Code/title from provided BU workbook (public catalog); description synthetic | J123: Calculus II is an introductory course in mathematics. It covers integration techniques, applications of integrals, improper integrals and sequences, and builds toward series and convergence tests. Students work through problem sets and proofs, with later units on power series and Taylor series. | K123: Explain the core ideas of integration techniques | Apply applications of integrals to solve standard problems | Analyze problems involving improper integrals | Use sequences in practical exercises | Evaluate approaches to series | Communicate findings about convergence tests | L123: integration techniques | applications of integrals | improper integrals | sequences | series | convergence tests | power series | Taylor series
A124: CAS MA 225 | B124: MA | C124: Multivariate Calculus | D124: Mathematics | E124: Lower division | F124: 200 | G124: 4 | I124: Code/title from provided BU workbook (public catalog); description synthetic | J124: Multivariate Calculus is an intermediate course in mathematics. It covers vectors, partial derivatives, gradients and multiple integrals, and builds toward vector fields and line integrals. Students work through problem sets and proofs, with later units on surface integrals and Green's and Stokes' theorems. | K124: Explain the core ideas of vectors | Apply partial derivatives to solve standard problems | Analyze problems involving gradients | Use multiple integrals in practical exercises | Evaluate approaches to vector fields | Communicate findings about line integrals | L124: vectors | partial derivatives | gradients | multiple integrals | vector fields | line integrals | surface integrals | Green's and Stokes' theorems
A125: CAS MA 242 | B125: MA | C125: Linear Algebra | D125: Mathematics | E125: Lower division | F125: 200 | G125: 4 | I125: Code/title from provided BU workbook (public catalog); description synthetic | J125: Linear Algebra is an intermediate course in mathematics. It covers linear systems, matrix algebra, determinants and vector spaces, and builds toward linear transformations and eigenvalues. Students work through problem sets and proofs, with later units on orthogonality and least squares. | K125: Explain the core ideas of linear systems | Apply matrix algebra to solve standard problems | Analyze problems involving determinants | Use vector spaces in practical exercises | Evaluate approaches to linear transformations | Communicate findings about eigenvalues | L125: linear systems | matrix algebra | determinants | vector spaces | linear transformations | eigenvalues | orthogonality | least squares
A126: CAS MA 226 | B126: MA | C126: Differential Equations | D126: Mathematics | E126: Lower division | F126: 200 | G126: 4 | I126: Code/title from provided BU workbook (public catalog); description synthetic | J126: Differential Equations is an intermediate course in mathematics. It covers first-order equations, second-order linear equations, systems of equations and Laplace transforms, and builds toward series solutions and stability. Students work through problem sets and proofs, with later units on mathematical modeling and numerical methods. | K126: Explain the core ideas of first-order equations | Apply second-order linear equations to solve standard problems | Analyze problems involving systems of equations | Use Laplace transforms in practical exercises | Evaluate approaches to series solutions | Communicate findings about stability | L126: first-order equations | second-order linear equations | systems of equations | Laplace transforms | series solutions | stability | mathematical modeling | numerical methods
A127: CAS MA 293 | B127: MA | C127: Discrete Mathematics | D127: Mathematics | E127: Lower division | F127: 200 | G127: 4 | I127: Code/title from provided BU workbook (public catalog); description synthetic | J127: Discrete Mathematics is an intermediate course in mathematics. It covers propositional logic, proof techniques, sets and functions and counting principles, and builds toward mathematical induction and relations. Students work through problem sets and proofs, with later units on graph basics and recurrence relations. | K127: Explain the core ideas of propositional logic | Apply proof techniques to solve standard problems | Analyze problems involving sets and functions | Use counting principles in practical exercises | Evaluate approaches to mathematical induction | Communicate findings about relations | L127: propositional logic | proof techniques | sets and functions | counting principles | mathematical induction | relations | graph basics | recurrence relations
A128: CAS MA 581 | B128: MA | C128: Probability | D128: Mathematics | E128: Upper division | F128: 300 | G128: 4 | I128: Code/title from provided BU workbook (public catalog); description synthetic | J128: Probability is an advanced course in mathematics. It covers probability axioms, random variables, expectation and variance and common distributions, and builds toward joint distributions and conditional probability. Students work through problem sets and proofs, with later units on limit theorems and moment generating functions. | K128: Explain the core ideas of probability axioms | Apply random variables to solve standard problems | Analyze problems involving expectation and variance | Use common distributions in practical exercises | Evaluate approaches to joint distributions | Communicate findings about conditional probability | L128: probability axioms | random variables | expectation and variance | common distributions | joint distributions | conditional probability | limit theorems | moment generating functions
A129: CAS MA 113 | B129: MA | C129: Elementary Statistics | D129: Mathematics | E129: Elective | F129: 100 | G129: 4 | I129: Fully synthetic course (not a real BU offering) | J129: Elementary Statistics is an introductory course in mathematics. It covers descriptive statistics, probability, sampling and confidence intervals, and builds toward hypothesis testing and correlation. Students work through problem sets and proofs, with later units on simple regression and data interpretation. | K129: Explain the core ideas of descriptive statistics | Apply probability to solve standard problems | Analyze problems involving sampling | Use confidence intervals in practical exercises | Evaluate approaches to hypothesis testing | Communicate findings about correlation | L129: descriptive statistics | probability | sampling | confidence intervals | hypothesis testing | correlation | simple regression | data interpretation
A130: CAS MA 115 | B130: MA | C130: Statistics 1 | D130: Mathematics | E130: Elective | F130: 100 | G130: 4 | I130: Fully synthetic course (not a real BU offering) | J130: Statistics 1 is an introductory course in mathematics. It covers descriptive statistics, probability, random variables and sampling distributions, and builds toward confidence intervals and hypothesis testing. Students work through problem sets and proofs, with later units on simple regression and statistical software. | K130: Explain the core ideas of descriptive statistics | Apply probability to solve standard problems | Analyze problems involving random variables | Use sampling distributions in practical exercises | Evaluate approaches to confidence intervals | Communicate findings about hypothesis testing | L130: descriptive statistics | probability | random variables | sampling distributions | confidence intervals | hypothesis testing | simple regression | statistical software
A131: CAS MA 116 | B131: MA | C131: Statistics 2 | D131: Mathematics | E131: Elective | F131: 100 | G131: 4 | I131: Fully synthetic course (not a real BU offering) | J131: Statistics 2 is an introductory course in mathematics. It covers multiple regression, analysis of variance, chi-square tests and nonparametric tests, and builds toward experimental design and model diagnostics. Students work through problem sets and proofs, with later units on categorical data and statistical software. | K131: Explain the core ideas of multiple regression | Apply analysis of variance to solve standard problems | Analyze problems involving chi-square tests | Use nonparametric tests in practical exercises | Evaluate approaches to experimental design | Communicate findings about model diagnostics | L131: multiple regression | analysis of variance | chi-square tests | nonparametric tests | experimental design | model diagnostics | categorical data | statistical software
A132: CAS MA 118 | B132: MA | C132: College Algebra and Trigonometry | D132: Mathematics | E132: Elective | F132: 100 | G132: 4 | I132: Fully synthetic course (not a real BU offering) | J132: College Algebra and Trigonometry is an introductory course in mathematics. It covers equations and inequalities, functions, polynomial functions and exponential functions, and builds toward logarithms and trigonometric functions. Students work through problem sets and proofs, with later units on trigonometric identities and systems of equations. | K132: Explain the core ideas of equations and inequalities | Apply functions to solve standard problems | Analyze problems involving polynomial functions | Use exponential functions in practical exercises | Evaluate approaches to logarithms | Communicate findings about trigonometric functions | L132: equations and inequalities | functions | polynomial functions | exponential functions | logarithms | trigonometric functions | trigonometric identities | systems of equations
A133: CAS MA 120 | B133: MA | C133: Applied Calculus | D133: Mathematics | E133: Elective | F133: 100 | G133: 4 | I133: Fully synthetic course (not a real BU offering) | J133: Applied Calculus is an introductory course in mathematics. It covers functions, limits, derivatives and applications of derivatives, and builds toward optimization and exponential models. Students work through problem sets and proofs, with later units on introduction to integrals and business applications. | K133: Explain the core ideas of functions | Apply limits to solve standard problems | Analyze problems involving derivatives | Use applications of derivatives in practical exercises | Evaluate approaches to optimization | Communicate findings about exponential models | L133: functions | limits | derivatives | applications of derivatives | optimization | exponential models | introduction to integrals | business applications
... A151: CAS MA 390 | B151: MA | C151: Optimization | D151: Mathematics | E151: Elective | F151: 300 | G151: 4 | I151: Fully synthetic course (not a real BU offering) | J151: Optimization is an advanced course in mathematics. It covers linear programming, simplex method, duality and integer programming, and builds toward network optimization and nonlinear optimization. Students work through problem sets and proofs, with later units on convexity and optimization software. | K151: Explain the core ideas of linear programming | Apply simplex method to solve standard problems | Analyze problems involving duality | Use integer programming in practical exercises | Evaluate approaches to network optimization | Communicate findings about nonlinear optimization | L151: linear programming | simplex method | duality | integer programming | network optimization | nonlinear optimization | convexity | optimization software

Sheet Schools
A1: School code | B1: Name | C1: Type | D1: Calendar | E1: Accreditation | F1: Location | G1: Role | H1: Note
A2: NEU | B2: Northeastern University | C2: Private research university (Boston) | D2: Semester | E2: Regionally accredited | F2: Boston, MA | G2: Primary source school (hackathon data) | H2: Real institution. Course codes/titles/credits from its public catalog via the hackathon workbook. Student records, grades and syllabi are synthetic and were NOT issued by Northeastern.
A3: NYU | B3: New York University | C3: Private research university (New York) | D3: Semester | E3: Regionally accredited | F3: New York, NY | G3: Primary source school (hackathon data) | H3: Real institution. Course codes/titles/credits from its public catalog via the hackathon workbook. Student records, grades and syllabi are synthetic and were NOT issued by NYU.
A4: PSC | B4: Pinecrest State College (fictional) | C4: Fictional four-year public college | D4: Quarter | E4: Regionally accredited | F4: Fictional | G4: Test helper: quarter-system conversion (NU and NYU use semesters) | H4: Fictional. Used for one summer course only.
A5: SOI | B5: Summit Online Institute (fictional) | C5: Fictional online institute | D5: Semester | E5: Not regionally accredited (national accreditor only) | F5: Online | G5: Test helper: accreditation rule | H5: Fictional. Used for the non-accredited-school test only.

Sheet External Courses
A1: Ext ID | B1: School | C1: Course code | D1: Title | E1: Credits | F1: Calendar | G1: Units if transferred | H1: Program area | I1: Course type | J1: Level | K1: Source | L1: Description | M1: Learning outcomes | N1: Topics | O1: gt_counterpart | P1: gt_overlap | Q1: gt_tier
A2: NEU|CS 2000 | B2: NEU | C2: CS 2000 | D2: Introduction to Program Design and Implementation | E2: 5 | F2: Semester | G2: 5 | H2: Computer Science | I2: Academic | J2: 200 | K2: NU catalog course (code/title/credits from hackathon workbook); description, outcomes and topics SYNTHETIC | L2: Introduction to Program Design and Implementation. Topics include recursion, debugging and testing, file input and output, functions and parameters and lists and strings; later weeks address conditionals and loops, problem decomposition and testing strategies. | M2: Explain the core ideas of recursion | Apply debugging and testing to solve standard problems | Analyze problems involving file input and output | Use functions and parameters in practical exercises | Evaluate approaches to lists and strings | Communicate findings about conditionals and loops | N2: recursion | debugging and testing | file input and output | functions and parameters | lists and strings | conditionals and loops | problem decomposition | testing strategies | O2: CAS CS 111 | P2: 0.875 | Q2: Equivalent (>=80%)
A3: NEU|CS 2100 | B3: NEU | C3: CS 2100 | D3: Program Design and Implementation 1 | E3: 5 | F3: Semester | G3: 5 | H3: Computer Science | I3: Academic | J3: 200 | K3: NU catalog course (code/title/credits from hackathon workbook); description, outcomes and topics SYNTHETIC | L3: Program Design and Implementation 1. Topics include discrete probability, algorithm efficiency, language paradigms, object-oriented programming and stacks and queues; later weeks address binary trees, sorting algorithms and cryptography basics. | M3: Explain the core ideas of discrete probability | Apply algorithm efficiency to solve standard problems | Analyze problems involving language paradigms | Use object-oriented programming in practical exercises | Evaluate approaches to stacks and queues | Communicate findings about binary trees | N3: discrete probability | algorithm efficiency | language paradigms | object-oriented programming | stacks and queues | binary trees | sorting algorithms | cryptography basics | O3: CAS CS 112 | P3: 0.625 | Q3: Evaluator decides (50-79%)
A4: NEU|CS 3100 | B4: NEU | C4: CS 3100 | D4: Program Design and Implementation 2 | E4: 5 | F4: Semester | G4: 5 | H4: Computer Science | I4: Academic | J4: 300 | K4: NU catalog course (code/title/credits from hackathon workbook); description, outcomes and topics SYNTHETIC | L4: Program Design and Implementation 2. Topics include cloud security, inheritance, UML modeling, runtime environments and refactoring; later weeks address modular arithmetic, classes and interfaces and unit testing. | M4: Explain the core ideas of cloud security | Apply inheritance to solve standard problems | Analyze problems involving UML modeling | Use runtime environments in practical exercises | Evaluate approaches to refactoring | Communicate findings about modular arithmetic | N4: cloud security | inheritance | UML modeling | runtime environments | refactoring | modular arithmetic | classes and interfaces | unit testing | O4: CAS CS 211 | P4: 0.625 | Q4: Evaluator decides (50-79%)
A5: NEU|CS 1800 | B5: NEU | C5: CS 1800 | D5: Discrete Structures | E5: 4 | F5: Semester | G5: 4 | H5: Computer Science | I5: Academic | J5: 100 | K5: NU catalog course (code/title/credits from hackathon workbook); description, outcomes and topics SYNTHETIC | L5: Discrete Structures. Topics include counting principles, propositional logic, proof techniques, graph basics and discrete probability; later weeks address sets and functions, mathematical induction and linking and loading. | M5: Explain the core ideas of counting principles | Apply propositional logic to solve standard problems | Analyze problems involving proof techniques | Use graph basics in practical exercises | Evaluate approaches to discrete probability | Communicate findings about sets and functions | N5: counting principles | propositional logic | proof techniques | graph basics | discrete probability | sets and functions | mathematical induction | linking and loading | O5: CAS CS 131 | P5: 0.875 | Q5: Equivalent (>=80%)
A6: NEU|CS 2700 | B6: NEU | C6: CS 2700 | D6: Data Structures and Analysis | E6: 5 | F6: Semester | G6: 5 | H6: Computer Science | I6: Academic | J6: 200 | K6: NU catalog course (code/title/credits from hackathon workbook); description, outcomes and topics SYNTHETIC | L6: Data Structures and Analysis. Topics include linked lists, data visualization, hash tables, algorithm efficiency and binary trees; later weeks address network security, object-oriented programming and sorting algorithms. | M6: Explain the core ideas of linked lists | Apply data visualization to solve standard problems | Analyze problems involving hash tables | Use algorithm efficiency in practical exercises | Evaluate approaches to binary trees | Communicate findings about network security | N6: linked lists | data visualization | hash tables | algorithm efficiency | binary trees | network security | object-oriented programming | sorting algorithms | O6: CAS CS 112 | P6: 0.75 | Q6: Evaluator decides (50-79%)
A7: NEU|CS 3000 | B7: NEU | C7: CS 3000 | D7: Algorithms and Data | E7: 4 | F7: Semester | G7: 4 | H7: Computer Science | I7: Academic | J7: 300 | K7: NU catalog course (code/title/credits from hackathon workbook); description, outcomes and topics SYNTHETIC | L7: Algorithms and Data. Topics include asymptotic analysis, greedy algorithms, dynamic programming, shortest paths and divide and conquer; later weeks address graph algorithms, network flow and NP-completeness. | M7: Explain the core ideas of asymptotic analysis | Apply greedy algorithms to solve standard problems | Analyze problems involving dynamic programming | Use shortest paths in practical exercises | Evaluate approaches to divide and conquer | Communicate findings about graph algorithms | N7: asymptotic analysis | greedy algorithms | dynamic programming | shortest paths | divide and conquer | graph algorithms | network flow | NP-completeness | O7: CAS CS 330 | P7: 1 | Q7: Equivalent (>=80%)
A8: NEU|CS 3650 | B8: NEU | C8: CS 3650 | D8: Computer Systems | E8: 4 | F8: Semester | G8: 4 | H8: Computer Science | I8: Academic | J8: 300 | K8: NU catalog course (code/title/credits from hackathon workbook); description, outcomes and topics SYNTHETIC | L8: Computer Systems. Topics include virtual memory, assembly language, linking and loading, memory hierarchy and binary data representation; later weeks address caches, processes and C programming. | M8: Explain the core ideas of virtual memory | Apply assembly language to solve standard problems | Analyze problems involving linking and loading | Use memory hierarchy in practical exercises | Evaluate approaches to binary data representation | Communicate findings about caches | N8: virtual memory | assembly language | linking and loading | memory hierarchy | binary data representation | caches | processes | C programming | O8: CAS CS 210 | P8: 1 | Q8: Equivalent (>=80%)
A9: NEU|CS 3800 | B9: NEU | C9: CS 3800 | D9: Theory of Computation | E9: 4 | F9: Semester | G9: 4 | H9: Computer Science | I9: Academic | J9: 300 | K9: NU catalog course (code/title/credits from hackathon workbook); description, outcomes and topics SYNTHETIC | L9: Theory of Computation. Topics include complexity classes, Turing machines, decidability, reductions and finite automata; later weeks address regular languages, pushdown automata and context-free grammars. | M9: Explain the core ideas of complexity classes | Apply Turing machines to solve standard problems | Analyze problems involving decidability | Use reductions in practical exercises | Evaluate approaches to finite automata | Communicate findings about regular languages | N9: complexity classes | Turing machines | decidability | reductions | finite automata | regular languages | pushdown automata | context-free grammars | O9: CAS CS 332 | P9: 1 | Q9: Equivalent (>=80%)
A10: NEU|CS 4400 | B10: NEU | C10: CS 4400 | D10: Programming Languages | E10: 4 | F10: Semester | G10: 4 | H10: Computer Science | I10: Academic | J10: 300 | K10: NU catalog course (code/title/credits from hackathon workbook); description, outcomes and topics SYNTHETIC | L10: Programming Languages. Topics include scoping and binding, parsing, language paradigms, semantics and type systems; later weeks address functional programming, syntax and grammars and interpreters. | M10: Explain the core ideas of scoping and binding | Apply parsing to solve standard problems | Analyze problems involving language paradigms | Use semantics in practical exercises | Evaluate approaches to type systems | Communicate findings about functional programming | N10: scoping and binding | parsing | language paradigms | semantics | type systems | functional programming | syntax and grammars | interpreters | O10: CAS CS 320 | P10: 1 | Q10: Equivalent (>=80%)
A11: NEU|CS 2800 | B11: NEU | C11: CS 2800 | D11: Logic and Computation | E11: 4 | F11: Semester | G11: 4 | H11: Computer Science | I11: Academic | J11: 200 | K11: NU catalog course (code/title/credits from hackathon workbook); description, outcomes and topics SYNTHETIC | L11: Logic and Computation. Topics include counting principles, online privacy, mathematical induction, reductions and exploratory analysis; later weeks address simulation, proof techniques and discrete probability. | M11: Explain the core ideas of counting principles | Apply online privacy to solve standard problems | Analyze problems involving mathematical induction | Use reductions in practical exercises | Evaluate approaches to exploratory analysis | Communicate findings about simulation | N11: counting principles | online privacy | mathematical induction | reductions | exploratory analysis | simulation | proof techniques | discrete probability | O11: CAS CS 131 | P11: 0.5 | Q11: Evaluator decides (50-79%)
A12: NEU|DS 3000 | B12: NEU | C12: DS 3000 | D12: Mathematical Foundations of Artificial Intelligence | E12: 4 | F12: Semester | G12: 4 | H12: Computer Science | I12: Academic | J12: 300 | K12: NU catalog course (code/title/credits from hackathon workbook); description, outcomes and topics SYNTHETIC | L12: Mathematical Foundations of Artificial Intelligence. Topics include virtualization, CSS, inheritance, linear regression and context-free grammars; later weeks address neural networks, polynomials and model evaluation. | M12: Explain the core ideas of virtualization | Apply CSS to solve standard problems | Analyze problems involving inheritance | Use linear regression in practical exercises | Evaluate approaches to context-free grammars | Communicate findings about neural networks | N12: virtualization | CSS | inheritance | linear regression | context-free grammars | neural networks | polynomials | model evaluation | O12: CAS CS 240 | P12: 0.375 | Q12: Elective (<50%)
A13: NEU|ECON 1116 | B13: NEU | C13: ECON 1116 | D13: Principles of Microeconomics | E13: 4 | F13: Semester | G13: 4 | H13: Economics | I13: Academic | J13: 100 | K13: NU catalog course (code/title/credits from hackathon workbook); description, outcomes and topics SYNTHETIC | L13: Principles of Microeconomics. Topics include monopoly, market failure, perfect competition, supply and demand and elasticity; later weeks address scarcity and opportunity cost, consumer choice and poverty measurement. | M13: Explain the core ideas of monopoly | Apply market failure to solve standard problems | Analyze problems involving perfect competition | Use supply and demand in practical exercises | Evaluate approaches to elasticity | Communicate findings about scarcity and opportunity cost | N13: monopoly | market failure | perfect competition | supply and demand | elasticity | scarcity and opportunity cost | consumer choice | poverty measurement | O13: CAS EC 101 | P13: 0.875 | Q13: Equivalent (>=80%)
... A171: NYU|ECON-UA 384 | B171: NYU | C171: ECON-UA 384 | D171: International Finance | E171: 4 | F171: Semester | G171: 4 | H171: Economics | I171: Academic | J171: 300 | K171: SYNTHETIC course (not in the NU/NYU catalog; invented for test volume) | L171: International Finance. Topics include open-economy macroeconomics, interest parity, capital flows, international institutions and balance of payments; later weeks address monetary unions, currency crises and exchange rates. | M171: Explain the core ideas of open-economy macroeconomics | Apply interest parity to solve standard problems | Analyze problems involving capital flows | Use international institutions in practical exercises | Evaluate approaches to balance of payments | Communicate findings about monetary unions | N171: open-economy macroeconomics | interest parity | capital flows | international institutions | balance of payments | monetary unions | currency crises | exchange rates | O171: CAS EC 340 | P171: 1 | Q171: Equivalent (>=80%)
A172: NEU|ENGW 1111 | B172: NEU | C172: ENGW 1111 | D172: First-Year Writing | E172: 4 | F172: Semester | G172: 4 | H172: General education | I172: Academic | J172: 100 | K172: SYNTHETIC course (not in the NU/NYU catalog; invented for test volume) | L172: First-Year Writing. Topics include thesis development, academic argument, research and citation, revision, audience and purpose and source evaluation. | M172: Explain the core ideas of thesis development | Apply academic argument to solve standard problems | Analyze problems involving research and citation | Use revision in practical exercises | Evaluate approaches to audience and purpose | Communicate findings about source evaluation | N172: thesis development | academic argument | research and citation | revision | audience and purpose | source evaluation | P172: 0 | Q172: No BU equivalent
A173: NEU|HIST 1130 | B173: NEU | C173: HIST 1130 | D173: Introduction to World History | E173: 4 | F173: Semester | G173: 4 | H173: General education | I173: Academic | J173: 100 | K173: SYNTHETIC course (not in the NU/NYU catalog; invented for test volume) | L173: Introduction to World History. Topics include ancient civilizations, classical empires, world religions, trade networks, colonialism and historical sources. | M173: Explain the core ideas of ancient civilizations | Apply classical empires to solve standard problems | Analyze problems involving world religions | Use trade networks in practical exercises | Evaluate approaches to colonialism | Communicate findings about historical sources | N173: ancient civilizations | classical empires | world religions | trade networks | colonialism | historical sources | P173: 0 | Q173: No BU equivalent
A174: NEU|SOCL 1101 | B174: NEU | C174: SOCL 1101 | D174: Introduction to Sociology | E174: 4 | F174: Semester | G174: 4 | H174: General education | I174: Academic | J174: 100 | K174: SYNTHETIC course (not in the NU/NYU catalog; invented for test volume) | L174: Introduction to Sociology. Topics include sociological imagination, culture, socialization, stratification, institutions and research methods. | M174: Explain the core ideas of sociological imagination | Apply culture to solve standard problems | Analyze problems involving socialization | Use stratification in practical exercises | Evaluate approaches to institutions | Communicate findings about research methods | N174: sociological imagination | culture | socialization | stratification | institutions | research methods | P174: 0 | Q174: No BU equivalent
A175: NEU|FILM 1101 | B175: NEU | C175: FILM 1101 | D175: Film Analysis | E175: 4 | F175: Semester | G175: 4 | H175: General education | I175: Academic | J175: 100 | K175: SYNTHETIC course (not in the NU/NYU catalog; invented for test volume) | L175: Film Analysis. Topics include film form, cinematography, editing, genre, film history and critical writing. | M175: Explain the core ideas of film form | Apply cinematography to solve standard problems | Analyze problems involving editing | Use genre in practical exercises | Evaluate approaches to film history | Communicate findings about critical writing | N175: film form | cinematography | editing | genre | film history | critical writing | P175: 0 | Q175: No BU equivalent
A176: NEU|MATH 0990 | B176: NEU | C176: MATH 0990 | D176: Algebra Foundations (developmental) | E176: 4 | F176: Semester | G176: 4 | H176: Mathematics | I176: Remedial | J176: 100 | K176: SYNTHETIC course (not in the NU/NYU catalog; invented for test volume) | L176: Algebra Foundations (developmental). Topics include linear equations, inequalities, polynomials, factoring, rational expressions and graphing. | M176: Explain the core ideas of linear equations | Apply inequalities to solve standard problems | Analyze problems involving polynomials | Use factoring in practical exercises | Evaluate approaches to rational expressions | Communicate findings about graphing | N176: linear equations | inequalities | polynomials | factoring | rational expressions | graphing | P176: 0 | Q176: No BU equivalent
A177: NEU|PE 1100 | B177: NEU | C177: PE 1100 | D177: Fitness Fundamentals | E177: 2 | F177: Semester | G177: 2 | H177: General education | I177: Physical education | J177: 100 | K177: SYNTHETIC course (not in the NU/NYU catalog; invented for test volume) | L177: Fitness Fundamentals. Topics include cardiovascular fitness, strength training, flexibility, nutrition basics, goal setting and wellness. | M177: Explain the core ideas of cardiovascular fitness | Apply strength training to solve standard problems | Analyze problems involving flexibility | Use nutrition basics in practical exercises | Evaluate approaches to goal setting | Communicate findings about wellness | N177: cardiovascular fitness | strength training | flexibility | nutrition basics | goal setting | wellness | P177: 0 | Q177: No BU equivalent
A178: NEU|FYS 1000 | B178: NEU | C178: FYS 1000 | D178: First-Year Seminar | E178: 1 | F178: Semester | G178: 1 | H178: General education | I178: Academic | J178: 100 | K178: SYNTHETIC course (not in the NU/NYU catalog; invented for test volume) | L178: First-Year Seminar. Topics include college transition, academic integrity, study strategies, campus resources, reflection and goal setting. | M178: Explain the core ideas of college transition | Apply academic integrity to solve standard problems | Analyze problems involving study strategies | Use campus resources in practical exercises | Evaluate approaches to reflection | Communicate findings about goal setting | N178: college transition | academic integrity | study strategies | campus resources | reflection | goal setting | P178: 0 | Q178: No BU equivalent
A179: NEU|MILS 1101 | B179: NEU | C179: MILS 1101 | D179: Military Science I (ROTC) | E179: 2 | F179: Semester | G179: 2 | H179: Military science | I179: ROTC | J179: 100 | K179: SYNTHETIC course (not in the NU/NYU catalog; invented for test volume) | L179: Military Science I (ROTC). Topics include military organization, leadership basics, land navigation, physical training, military history and values and ethics. | M179: Explain the core ideas of military organization | Apply leadership basics to solve standard problems | Analyze problems involving land navigation | Use physical training in practical exercises | Evaluate approaches to military history | Communicate findings about values and ethics | N179: military organization | leadership basics | land navigation | physical training | military history | values and ethics | P179: 0 | Q179: No BU equivalent
A180: NEU|COOP 3945 | B180: NEU | C180: COOP 3945 | D180: Co-op Work Experience | E180: 4 | F180: Semester | G180: 4 | H180: Career | I180: Internship | J180: 100 | K180: SYNTHETIC course (not in the NU/NYU catalog; invented for test volume) | L180: Co-op Work Experience. Topics include workplace learning, professional skills, reflective journal, supervisor evaluation, career planning and final report. | M180: Explain the core ideas of workplace learning | Apply professional skills to solve standard problems | Analyze problems involving reflective journal | Use supervisor evaluation in practical exercises | Evaluate approaches to career planning | Communicate findings about final report | N180: workplace learning | professional skills | reflective journal | supervisor evaluation | career planning | final report | P180: 0 | Q180: No BU equivalent
A181: NEU|BIOL 4990 | B181: NEU | C181: BIOL 4990 | D181: Directed Research in Biology | E181: 4 | F181: Semester | G181: 4 | H181: Biology | I181: Research | J181: 100 | K181: SYNTHETIC course (not in the NU/NYU catalog; invented for test volume) | L181: Directed Research in Biology. Topics include research design, literature review, laboratory work, data analysis, scientific writing and poster presentation. | M181: Explain the core ideas of research design | Apply literature review to solve standard problems | Analyze problems involving laboratory work | Use data analysis in practical exercises | Evaluate approaches to scientific writing | Communicate findings about poster presentation | N181: research design | literature review | laboratory work | data analysis | scientific writing | poster presentation | P181: 0 | Q181: No BU equivalent
A182: NEU|CS 1990 | B182: NEU | C182: CS 1990 | D182: Introduction to Programming in Python | E182: 4 | F182: Semester | G182: 4 | H182: Computer Science | I182: Academic | J182: 100 | K182: SYNTHETIC course (not in the NU/NYU catalog; invented for test volume) | L182: Introduction to Programming in Python. Topics include variables and expressions, conditionals and loops, functions and parameters, lists and strings, file input and output and debugging and testing. | M182: Explain the core ideas of variables and expressions | Apply conditionals and loops to solve standard problems | Analyze problems involving functions and parameters | Use lists and strings in practical exercises | Evaluate approaches to file input and output | Communicate findings about debugging and testing | N182: variables and expressions | conditionals and loops | functions and parameters | lists and strings | file input and output | debugging and testing | O182: CAS CS 111 | P182: 0.75 | Q182: Duplicate of CS 111 content
A183: NYU|WRIT-UA 5 | B183: NYU | C183: WRIT-UA 5 | D183: Writing Workshop | E183: 4 | F183: Semester | G183: 4 | H183: General education | I183: Academic | J183: 100 | K183: SYNTHETIC course (not in the NU/NYU catalog; invented for test volume) | L183: Writing Workshop. Topics include academic argument, research and citation, source evaluation, revision, genre analysis and peer review. | M183: Explain the core ideas of academic argument | Apply research and citation to solve standard problems | Analyze problems involving source evaluation | Use revision in practical exercises | Evaluate approaches to genre analysis | Communicate findings about peer review | N183: academic argument | research and citation | source evaluation | revision | genre analysis | peer review | P183: 0 | Q183: No BU equivalent
A184: NYU|HIST-UA 10 | B184: NYU | C184: HIST-UA 10 | D184: Modern World History | E184: 4 | F184: Semester | G184: 4 | H184: General education | I184: Academic | J184: 100 | K184: SYNTHETIC course (not in the NU/NYU catalog; invented for test volume) | L184: Modern World History. Topics include industrialization, world wars, decolonization, Cold War, globalization and historical sources. | M184: Explain the core ideas of industrialization | Apply world wars to solve standard problems | Analyze problems involving decolonization | Use Cold War in practical exercises | Evaluate approaches to globalization | Communicate findings about historical sources | N184: industrialization | world wars | decolonization | Cold War | globalization | historical sources | P184: 0 | Q184: No BU equivalent
A185: NYU|PHIL-UA 3 | B185: NYU | C185: PHIL-UA 3 | D185: Introduction to Ethics | E185: 4 | F185: Semester | G185: 4 | H185: General education | I185: Academic | J185: 100 | K185: SYNTHETIC course (not in the NU/NYU catalog; invented for test volume) | L185: Introduction to Ethics. Topics include ethical theories, utilitarianism, deontology, virtue ethics, applied ethics and moral argument. | M185: Explain the core ideas of ethical theories | Apply utilitarianism to solve standard problems | Analyze problems involving deontology | Use virtue ethics in practical exercises | Evaluate approaches to applied ethics | Communicate findings about moral argument | N185: ethical theories | utilitarianism | deontology | virtue ethics | applied ethics | moral argument | P185: 0 | Q185: No BU equivalent
A186: NYU|SPAN-UA 1 | B186: NYU | C186: SPAN-UA 1 | D186: Elementary Spanish I | E186: 4 | F186: Semester | G186: 4 | H186: General education | I186: Academic | J186: 100 | K186: SYNTHETIC course (not in the NU/NYU catalog; invented for test volume) | L186: Elementary Spanish I. Topics include pronunciation, present tense, everyday vocabulary, conversation, Hispanic cultures and reading short texts. | M186: Explain the core ideas of pronunciation | Apply present tense to solve standard problems | Analyze problems involving everyday vocabulary | Use conversation in practical exercises | Evaluate approaches to Hispanic cultures | Communicate findings about reading short texts | N186: pronunciation | present tense | everyday vocabulary | conversation | Hispanic cultures | reading short texts | P186: 0 | Q186: No BU equivalent
A187: NYU|ART-UA 5 | B187: NYU | C187: ART-UA 5 | D187: Art Appreciation | E187: 4 | F187: Semester | G187: 4 | H187: General education | I187: Academic | J187: 100 | K187: SYNTHETIC course (not in the NU/NYU catalog; invented for test volume) | L187: Art Appreciation. Topics include visual elements, art media, art history overview, museum analysis, design principles and art criticism. | M187: Explain the core ideas of visual elements | Apply art media to solve standard problems | Analyze problems involving art history overview | Use museum analysis in practical exercises | Evaluate approaches to design principles | Communicate findings about art criticism | N187: visual elements | art media | art history overview | museum analysis | design principles | art criticism | P187: 0 | Q187: No BU equivalent
A188: NYU|COMM-UA 10 | B188: NYU | C188: COMM-UA 10 | D188: Public Speaking | E188: 4 | F188: Semester | G188: 4 | H188: General education | I188: Academic | J188: 100 | K188: SYNTHETIC course (not in the NU/NYU catalog; invented for test volume) | L188: Public Speaking. Topics include speech organization, audience analysis, delivery, persuasive speaking, visual aids and speech anxiety. | M188: Explain the core ideas of speech organization | Apply audience analysis to solve standard problems | Analyze problems involving delivery | Use persuasive speaking in practical exercises | Evaluate approaches to visual aids | Communicate findings about speech anxiety | N188: speech organization | audience analysis | delivery | persuasive speaking | visual aids | speech anxiety | P188: 0 | Q188: No BU equivalent
A189: NYU|ECON-UA 980 | B189: NYU | C189: ECON-UA 980 | D189: Economics Internship | E189: 4 | F189: Semester | G189: 4 | H189: Economics | I189: Internship | J189: 100 | K189: SYNTHETIC course (not in the NU/NYU catalog; invented for test volume) | L189: Economics Internship. Topics include workplace learning, professional skills, reflective journal, supervisor evaluation, career planning and final report. | M189: Explain the core ideas of workplace learning | Apply professional skills to solve standard problems | Analyze problems involving reflective journal | Use supervisor evaluation in practical exercises | Evaluate approaches to career planning | Communicate findings about final report | N189: workplace learning | professional skills | reflective journal | supervisor evaluation | career planning | final report | P189: 0 | Q189: No BU equivalent
A190: NYU|PHED-UA 10 | B190: NYU | C190: PHED-UA 10 | D190: Fitness and Wellness | E190: 2 | F190: Semester | G190: 2 | H190: General education | I190: Physical education | J190: 100 | K190: SYNTHETIC course (not in the NU/NYU catalog; invented for test volume) | L190: Fitness and Wellness. Topics include cardiovascular fitness, strength training, flexibility, nutrition basics, goal setting and wellness. | M190: Explain the core ideas of cardiovascular fitness | Apply strength training to solve standard problems | Analyze problems involving flexibility | Use nutrition basics in practical exercises | Evaluate approaches to goal setting | Communicate findings about wellness | N190: cardiovascular fitness | strength training | flexibility | nutrition basics | goal setting | wellness | P190: 0 | Q190: No BU equivalent
A191: NYU|MATH-UA 9 | B191: NYU | C191: MATH-UA 9 | D191: Algebra and Calculus Foundations (developmental) | E191: 4 | F191: Semester | G191: 4 | H191: Mathematics | I191: Remedial | J191: 100 | K191: SYNTHETIC course (not in the NU/NYU catalog; invented for test volume) | L191: Algebra and Calculus Foundations (developmental). Topics include linear equations, functions, polynomials, exponential functions, logarithms and graphing. | M191: Explain the core ideas of linear equations | Apply functions to solve standard problems | Analyze problems involving polynomials | Use exponential functions in practical exercises | Evaluate approaches to logarithms | Communicate findings about graphing | N191: linear equations | functions | polynomials | exponential functions | logarithms | graphing | P191: 0 | Q191: No BU equivalent
A192: NYU|PSYCH-UA 997 | B192: NYU | C192: PSYCH-UA 997 | D192: Independent Research in Psychology | E192: 4 | F192: Semester | G192: 4 | H192: Psychology | I192: Research | J192: 100 | K192: SYNTHETIC course (not in the NU/NYU catalog; invented for test volume) | L192: Independent Research in Psychology. Topics include research design, literature review, data collection, data analysis, scientific writing and presentation. | M192: Explain the core ideas of research design | Apply literature review to solve standard problems | Analyze problems involving data collection | Use data analysis in practical exercises | Evaluate approaches to scientific writing | Communicate findings about presentation | N192: research design | literature review | data collection | data analysis | scientific writing | presentation | P192: 0 | Q192: No BU equivalent
A193: PSC|PSY 215 | B193: PSC | C193: PSY 215 | D193: Psychology of Music | E193: 4 | F193: Quarter | G193: 2.67 | H193: Psychology | I193: Academic | J193: 100 | K193: Fictional helper school (synthetic) | L193: Psychology of Music. Topics include music perception, emotion and music, music and memory, musical development, music therapy and cultural differences in music. | M193: Explain the core ideas of music perception | Apply emotion and music to solve standard problems | Analyze problems involving music and memory | Use musical development in practical exercises | Evaluate approaches to music therapy | Communicate findings about cultural differences in music | N193: music perception | emotion and music | music and memory | musical development | music therapy | cultural differences in music | P193: 0 | Q193: No BU equivalent
A194: SOI|ECO 210 | B194: SOI | C194: ECO 210 | D194: Personal Finance | E194: 3 | F194: Semester | G194: 3 | H194: Economics | I194: Academic | J194: 100 | K194: Fictional helper school (synthetic) | L194: Personal Finance. Topics include budgeting, credit, saving and investing, insurance, taxes and retirement planning. | M194: Explain the core ideas of budgeting | Apply credit to solve standard problems | Analyze problems involving saving and investing | Use insurance in practical exercises | Evaluate approaches to taxes | Communicate findings about retirement planning | N194: budgeting | credit | saving and investing | insurance | taxes | retirement planning | P194: 0 | Q194: No BU equivalent
A195: SOI|BUS 101 | B195: SOI | C195: BUS 101 | D195: Introduction to Business | E195: 3 | F195: Semester | G195: 3 | H195: General education | I195: Academic | J195: 100 | K195: Fictional helper school (synthetic) | L195: Introduction to Business. Topics include business functions, management, marketing, accounting basics, entrepreneurship and business ethics. | M195: Explain the core ideas of business functions | Apply management to solve standard problems | Analyze problems involving marketing | Use accounting basics in practical exercises | Evaluate approaches to entrepreneurship | Communicate findings about business ethics | N195: business functions | management | marketing | accounting basics | entrepreneurship | business ethics | P195: 0 | Q195: No BU equivalent

Sheet Past Decisions
A1: Decision ID | B1: Ext ID | C1: School | D1: Source course | E1: Source title | F1: Source credits | G1: Calendar | H1: Decision | I1: BU course | J1: Units awarded | K1: BU grade | L1: Reason code | M1: Overlap % | N1: Decided by | O1: Department | P1: Decision date | Q1: Catalog year | R1: Reusable | S1: Split | T1: Notes
A2: D-0001 | B2: NYU|PSYCH-UA 1 | C2: NYU | D2: PSYCH-UA 1 | E2: Intro to Psychology | F2: 4 | G2: Semester | H2: Equivalent | I2: CAS PS 101 | J2: 4 | K2: T | L2: EQ-CONTENT | M2: 88 | N2: Evaluator PS-A | O2: Psychology | P2: 2025-08-02 | Q2: 2024-25 | R2: Yes | S2: train
A3: D-0002 | B3: NYU|MATH-UA 121 | C3: NYU | D3: MATH-UA 121 | E3: Calculus I | F3: 4 | G3: Semester | H3: Equivalent | I3: CAS MA 123 | J3: 4 | K3: T | L3: EQ-CONTENT | M3: 100 | N3: Evaluator MA-B | O3: Mathematics | P3: 2024-12-08 | Q3: 2024-25 | R3: Yes | S3: train
A4: D-0003 | B4: NYU|ECON-UA 2 | C4: NYU | D4: ECON-UA 2 | E4: Introduction to Microeconomics | F4: 4 | G4: Semester | H4: Equivalent | I4: CAS EC 101 | J4: 4 | K4: T | L4: EQ-CONTENT | M4: 88 | N4: Evaluator EC-B | O4: Economics | P4: 2024-05-25 | Q4: 2024-25 | R4: Yes | S4: train
A5: D-0004 | B5: PSC|PSY 215 | C5: PSC | D5: PSY 215 | E5: Psychology of Music | F5: 4 | G5: Quarter | H5: Elective | I5: CAS PS 2TR | J5: 2.67 | K5: T | L5: EL-NOEQUIV | N5: Evaluator PS-A | O5: Psychology | P5: 2025-03-22 | Q5: 2023-24 | R5: Yes | S5: train
A6: D-0005 | B6: NEU|HIST 1130 | C6: NEU | D6: HIST 1130 | E6: Introduction to World History | F6: 4 | G6: Semester | H6: Elective | I6: TFRGEN 1TR | J6: 4 | K6: T | L6: EL-NOEQUIV | N6: Credit Evaluation Office | O6: General education | P6: 2024-05-19 | Q6: 2023-24 | R6: Yes | S6: train
A7: D-0006 | B7: NEU|CS 2000 | C7: NEU | D7: CS 2000 | E7: Introduction to Program Design and Implementation | F7: 5 | G7: Semester | H7: Equivalent | I7: CAS CS 111 | J7: 5 | K7: T | L7: EQ-CONTENT | M7: 88 | N7: Evaluator CS-A | O7: Computer Science | P7: 2025-11-01 | Q7: 2024-25 | R7: Yes | S7: train
A8: D-0007 | B8: NEU|MATH 1341 | C8: NEU | D8: MATH 1341 | E8: Calculus 1 for Science and Engineering | F8: 4 | G8: Semester | H8: Equivalent | I8: CAS MA 123 | J8: 4 | K8: T | L8: EQ-CONTENT | M8: 88 | N8: Evaluator MA-B | O8: Mathematics | P8: 2025-06-24 | Q8: 2024-25 | R8: Yes | S8: train
A9: D-0008 | B9: NEU|MATH 0990 | C9: NEU | D9: MATH 0990 | E9: Algebra Foundations (developmental) | F9: 4 | G9: Semester | H9: No credit | I9: TFRGEN NOCRDT | J9: 0 | K9: TX | L9: NC-REMEDIAL | N9: Credit Evaluation Office | O9: Mathematics | P9: 2024-09-22 | Q9: 2024-25 | R9: Yes | S9: train
A10: D-0009 | B10: NEU|PE 1100 | C10: NEU | D10: PE 1100 | E10: Fitness Fundamentals | F10: 2 | G10: Semester | H10: No credit | I10: TFRGEN NOCRDT | J10: 0 | K10: TX | L10: NC-PE | N10: Credit Evaluation Office | O10: General education | P10: 2025-03-05 | Q10: 2023-24 | R10: Yes | S10: train
A11: D-0010 | B11: NEU|FYS 1000 | C11: NEU | D11: FYS 1000 | E11: First-Year Seminar | F11: 1 | G11: Semester | H11: No credit | I11: TFRGEN NOCRDT | J11: 0 | K11: TX | L11: NC-ONECREDIT | N11: Credit Evaluation Office | O11: General education | P11: 2024-11-09 | Q11: 2023-24 | R11: Yes | S11: train
A12: D-0011 | B12: NEU|CS 1800 | C12: NEU | D12: CS 1800 | E12: Discrete Structures | F12: 4 | G12: Semester | H12: Equivalent | I12: CAS CS 131 | J12: 4 | K12: T | L12: EQ-CONTENT | M12: 88 | N12: Evaluator CS-B | O12: Computer Science | P12: 2024-10-15 | Q12: 2024-25 | R12: Yes | S12: train
A13: D-0012 | B13: NEU|CS 1990 | C13: NEU | D13: CS 1990 | E13: Introduction to Programming in Python | F13: 4 | G13: Semester | H13: Equivalent | I13: CAS CS 111 | J13: 4 | K13: T | L13: EQ-EVALUATOR | M13: 75 | N13: Evaluator CS-A | O13: Computer Science | P13: 2025-04-10 | Q13: 2023-24 | R13: Yes | S13: train
A14: D-0013 | B14: NEU|FILM 1101 | C14: NEU | D14: FILM 1101 | E14: Film Analysis | F14: 4 | G14: Semester | H14: Elective | I14: TFRGEN 1TR | J14: 4 | K14: T | L14: EL-NOEQUIV | N14: Credit Evaluation Office | O14: General education | P14: 2025-03-26 | Q14: 2023-24 | R14: Yes | S14: train
A15: D-0014 | B15: NEU|CS 3650 | C15: NEU | D15: CS 3650 | E15: Computer Systems | F15: 4 | G15: Semester | H15: Equivalent | I15: CAS CS 210 | J15: 4 | K15: T | L15: EQ-CONTENT | M15: 100 | N15: Evaluator CS-B | O15: Computer Science | P15: 2024-10-20 | Q15: 2024-25 | R15: Yes | S15: train
A16: D-0015 | B16: NEU|CS 4400 | C16: NEU | D16: CS 4400 | E16: Programming Languages | F16: 4 | G16: Semester | H16: Elective | I16: CAS CS 2TR | J16: 4 | K16: T | L16: EL-RESIDENCY | M16: 100 | N16: Evaluator CS-B | O16: Computer Science | P16: 2024-12-14 | Q16: 2023-24 | R16: Yes | S16: train
A17: D-0016 | B17: NEU|MATH 2331 | C17: NEU | D17: MATH 2331 | E17: Linear Algebra | F17: 4 | G17: Semester | H17: Equivalent | I17: CAS MA 242 | J17: 4 | K17: T | L17: EQ-CONTENT | M17: 100 | N17: Evaluator MA-A | O17: Mathematics | P17: 2024-05-17 | Q17: 2023-24 | R17: Yes | S17: train
A18: D-0017 | B18: NEU|BIOL 1107 | C18: NEU | D18: BIOL 1107 | E18: Foundations of Biology | F18: 5 | G18: Semester | H18: Equivalent | I18: CAS BI 107 | J18: 5 | K18: T | L18: EQ-CONTENT | M18: 88 | N18: Evaluator BI-A | O18: Biology | P18: 2024-06-27 | Q18: 2023-24 | R18: Yes | S18: train
A19: D-0018 | B19: NEU|ENGW 1111 | C19: NEU | D19: ENGW 1111 | E19: First-Year Writing | F19: 4 | G19: Semester | H19: Elective | I19: TFRGEN 1TR | J19: 4 | K19: T | L19: EL-NOEQUIV | N19: Credit Evaluation Office | O19: General education | P19: 2025-09-15 | Q19: 2024-25 | R19: Yes | S19: train
A20: D-0019 | B20: NEU|BIOL 1113 | C20: NEU | D20: BIOL 1113 | E20: General Biology 2 | F20: 4 | G20: Semester | H20: Equivalent | I20: CAS BI 108 | J20: 4 | K20: T | L20: EQ-CONTENT | M20: 100 | N20: Evaluator BI-A | O20: Biology | P20: 2024-01-12 | Q20: 2023-24 | R20: Yes | S20: train
A21: D-0020 | B21: NEU|BIOL 2703 | C21: NEU | D21: BIOL 2703 | E21: Microbiology | F21: 5 | G21: Semester | H21: Equivalent | I21: CAS BI 210 | J21: 5 | K21: T | L21: EQ-CONTENT | M21: 88 | N21: Evaluator BI-A | O21: Biology | P21: 2024-11-05 | Q21: 2024-25 | R21: Yes | S21: train
A22: D-0021 | B22: NEU|BIOL 2703 | C22: NEU | D22: BIOL 2703 | E22: Microbiology | F22: 5 | G22: Semester | H22: Elective | I22: CAS BI 2TR | J22: 5 | K22: T | L22: EL-PARTIAL | M22: 88 | N22: Evaluator BI-B | O22: Biology | P22: 2025-06-02 | Q22: 2024-25 | R22: Yes | S22: train | T22: Conflicts with an earlier decision in the same catalog year
A23: D-0022 | B23: NEU|CHEM 2313 | C23: NEU | D23: CHEM 2313 | E23: Organic Chemistry 2 | F23: 5 | G23: Semester | H23: Equivalent | I23: CAS CH 204 | J23: 5 | K23: T | L23: EQ-CONTENT | M23: 100 | N23: Evaluator BI-B | O23: Biology | P23: 2025-08-10 | Q23: 2024-25 | R23: Yes | S23: train
A24: D-0023 | B24: NEU|BIOL 4990 | C24: NEU | D24: BIOL 4990 | E24: Directed Research in Biology | F24: 4 | G24: Semester | H24: No credit | I24: TFRGEN NOCRDT | J24: 0 | K24: TX | L24: NC-RESEARCH | N24: Credit Evaluation Office | O24: Biology | P24: 2024-01-23 | Q24: 2023-24 | R24: Yes | S24: train
A25: D-0024 | B25: NEU|ECON 1116 | C25: NEU | D25: ECON 1116 | E25: Principles of Microeconomics | F25: 4 | G25: Semester | H25: Equivalent | I25: CAS EC 101 | J25: 4 | K25: T | L25: EQ-CONTENT | M25: 88 | N25: Evaluator EC-A | O25: Economics | P25: 2024-01-05 | Q25: 2023-24 | R25: Yes | S25: train
A26: D-0025 | B26: NEU|MILS 1101 | C26: NEU | D26: MILS 1101 | E26: Military Science I (ROTC) | F26: 2 | G26: Semester | H26: No credit | I26: TFRGEN NOCRDT | J26: 0 | K26: TX | L26: NC-ROTC | N26: Credit Evaluation Office | O26: Military science | P26: 2024-01-20 | Q26: 2023-24 | R26: Yes | S26: train
A27: D-0026 | B27: NEU|ECON 1115 | C27: NEU | D27: ECON 1115 | E27: Principles of Macroeconomics | F27: 4 | G27: Semester | H27: Equivalent | I27: CAS EC 102 | J27: 4 | K27: T | L27: EQ-CONTENT | M27: 100 | N27: Evaluator EC-A | O27: Economics | P27: 2025-06-26 | Q27: 2024-25 | R27: Yes | S27: train
A28: D-0027 | B28: NEU|MATH 1342 | C28: NEU | D28: MATH 1342 | E28: Calculus 2 for Science and Engineering | F28: 4 | G28: Semester | H28: Equivalent | I28: CAS MA 124 | J28: 4 | K28: T | L28: EQ-CONTENT | M28: 88 | N28: Evaluator MA-B | O28: Mathematics | P28: 2025-02-05 | Q28: 2023-24 | R28: Yes | S28: train
A29: D-0028 | B29: NEU|SOCL 1101 | C29: NEU | D29: SOCL 1101 | E29: Introduction to Sociology | F29: 4 | G29: Semester | H29: Elective | I29: TFRGEN 1TR | J29: 4 | K29: T | L29: EL-NOEQUIV | N29: Credit Evaluation Office | O29: General education | P29: 2025-03-27 | Q29: 2024-25 | R29: Yes | S29: train
A30: D-0029 | B30: SOI|ECO 210 | C30: SOI | D30: ECO 210 | E30: Personal Finance | F30: 3 | G30: Semester | H30: No credit | I30: TFRGEN NOCRDT | J30: 0 | K30: TX | L30: NC-ACCRED | N30: Evaluator EC-A | O30: Economics | P30: 2024-12-09 | Q30: 2024-25 | R30: Yes | S30: train
A31: D-0030 | B31: SOI|BUS 101 | C31: SOI | D31: BUS 101 | E31: Introduction to Business | F31: 3 | G31: Semester | H31: No credit | I31: TFRGEN NOCRDT | J31: 0 | K31: TX | L31: NC-ACCRED | N31: Credit Evaluation Office | O31: General education | P31: 2024-02-13 | Q31: 2023-24 | R31: Yes | S31: train
A32: D-0031 | B32: NYU|COMM-UA 10 | C32: NYU | D32: COMM-UA 10 | E32: Public Speaking | F32: 4 | G32: Semester | H32: Elective | I32: TFRGEN 1TR | J32: 4 | K32: T | L32: EL-NOEQUIV | N32: Credit Evaluation Office | O32: General education | P32: 2025-05-28 | Q32: 2023-24 | R32: Yes | S32: train
A33: D-0032 | B33: NYU|ART-UA 5 | C33: NYU | D33: ART-UA 5 | E33: Art Appreciation | F33: 4 | G33: Semester | H33: Elective | I33: TFRGEN 1TR | J33: 4 | K33: T | L33: EL-NOEQUIV | N33: Credit Evaluation Office | O33: General education | P33: 2025-07-26 | Q33: 2023-24 | R33: Yes | S33: train
A34: D-0033 | B34: NYU|SPAN-UA 1 | C34: NYU | D34: SPAN-UA 1 | E34: Elementary Spanish I | F34: 4 | G34: Semester | H34: Elective | I34: TFRGEN 1TR | J34: 4 | K34: T | L34: EL-NOEQUIV | N34: Credit Evaluation Office | O34: General education | P34: 2024-03-03 | Q34: 2023-24 | R34: Yes | S34: train
A35: D-0034 | B35: NYU|ECON-UA 10 | C35: NYU | D35: ECON-UA 10 | E35: Intermediate Microeconomics | F35: 4 | G35: Semester | H35: Equivalent | I35: CAS EC 201 | J35: 4 | K35: T | L35: EQ-CONTENT | M35: 88 | N35: Evaluator EC-A | O35: Economics | P35: 2025-07-14 | Q35: 2023-24 | R35: Yes | S35: train
A36: D-0035 | B36: NYU|PHIL-UA 3 | C36: NYU | D36: PHIL-UA 3 | E36: Introduction to Ethics | F36: 4 | G36: Semester | H36: Elective | I36: TFRGEN 1TR | J36: 4 | K36: T | L36: EL-NOEQUIV | N36: Credit Evaluation Office | O36: General education | P36: 2024-11-11 | Q36: 2024-25 | R36: Yes | S36: train
A37: D-0036 | B37: NYU|ECON-UA 12 | C37: NYU | D37: ECON-UA 12 | E37: Intermediate Macroeconomics | F37: 4 | G37: Semester | H37: Equivalent | I37: CAS EC 202 | J37: 4 | K37: T | L37: EQ-CONTENT | M37: 100 | N37: Evaluator EC-A | O37: Economics | P37: 2024-09-05 | Q37: 2024-25 | R37: Yes | S37: train
A38: D-0037 | B38: NYU|ECON-UA 18 | C38: NYU | D38: ECON-UA 18 | E38: Statistics | F38: 4 | G38: Semester | H38: Elective | I38: CAS EC 2TR | J38: 4 | K38: T | L38: EL-PARTIAL | M38: 100 | N38: Evaluator EC-A | O38: Economics | P38: 2023-03-14 | Q38: 2022-23 | R38: Yes | S38: train | T38: Older decision; superseded
A39: D-0038 | B39: NYU|ECON-UA 18 | C39: NYU | D39: ECON-UA 18 | E39: Statistics | F39: 4 | G39: Semester | H39: Equivalent | I39: CAS EC 203 | J39: 4 | K39: T | L39: EQ-EVALUATOR | M39: 100 | N39: Evaluator EC-B | O39: Economics | P39: 2025-02-10 | Q39: 2024-25 | R39: Yes | S39: train | T39: Newer decision for later catalog year
A40: D-0039 | B40: NYU|MATH-UA 140 | C40: NYU | D40: MATH-UA 140 | E40: Linear Algebra | F40: 4 | G40: Semester | H40: Equivalent | I40: CAS MA 242 | J40: 4 | K40: T | L40: EQ-CONTENT | M40: 100 | N40: Evaluator MA-A | O40: Mathematics | P40: 2024-05-14 | Q40: 2024-25 | R40: Yes | S40: train
A41: D-0040 | B41: NYU|ECON-UA 163 | C41: NYU | D41: ECON-UA 163 | E41: Money and Banking | F41: 4 | G41: Semester | H41: Equivalent | I41: CAS EC 220 | J41: 4 | K41: T | L41: EQ-CONTENT | M41: 100 | N41: Evaluator EC-B | O41: Economics | P41: 2025-02-05 | Q41: 2024-25 | R41: Yes | S41: train
A42: D-0041 | B42: NYU|ECON-UA 166 | C42: NYU | D42: ECON-UA 166 | E42: International Trade | F42: 4 | G42: Semester | H42: Equivalent | I42: CAS EC 250 | J42: 4 | K42: T | L42: EQ-CONTENT | M42: 88 | N42: Evaluator EC-B | O42: Economics | P42: 2024-05-19 | Q42: 2023-24 | R42: Yes | S42: train
A43: D-0042 | B43: NYU|ECON-UA 980 | C43: NYU | D43: ECON-UA 980 | E43: Economics Internship | F43: 4 | G43: Semester | H43: No credit | I43: TFRGEN NOCRDT | J43: 0 | K43: TX | L43: NC-INTERNSHIP | N43: Credit Evaluation Office | O43: Economics | P43: 2024-11-21 | Q43: 2023-24 | R43: Yes | S43: train
A44: D-0043 | B44: NYU|WRIT-UA 5 | C44: NYU | D44: WRIT-UA 5 | E44: Writing Workshop | F44: 4 | G44: Semester | H44: Elective | I44: TFRGEN 1TR | J44: 4 | K44: T | L44: EL-NOEQUIV | N44: Credit Evaluation Office | O44: General education | P44: 2025-12-23 | Q44: 2024-25 | R44: Yes | S44: train
A45: D-0044 | B45: NYU|HIST-UA 10 | C45: NYU | D45: HIST-UA 10 | E45: Modern World History | F45: 4 | G45: Semester | H45: Elective | I45: TFRGEN 1TR | J45: 4 | K45: T | L45: EL-NOEQUIV | N45: Credit Evaluation Office | O45: General education | P45: 2024-04-06 | Q45: 2024-25 | R45: Yes | S45: train
A46: D-0045 | B46: NYU|PHED-UA 10 | C46: NYU | D46: PHED-UA 10 | E46: Fitness and Wellness | F46: 2 | G46: Semester | H46: No credit | I46: TFRGEN NOCRDT | J46: 0 | K46: TX | L46: NC-PE | N46: Credit Evaluation Office | O46: General education | P46: 2024-11-05 | Q46: 2024-25 | R46: Yes | S46: train
A47: D-0046 | B47: NYU|MATH-UA 9 | C47: NYU | D47: MATH-UA 9 | E47: Algebra and Calculus Foundations (developmental) | F47: 4 | G47: Semester | H47: No credit | I47: TFRGEN NOCRDT | J47: 0 | K47: TX | L47: NC-REMEDIAL | N47: Credit Evaluation Office | O47: Mathematics | P47: 2024-07-26 | Q47: 2023-24 | R47: Yes | S47: train
A48: D-0047 | B48: NYU|PSYCH-UA 997 | C48: NYU | D48: PSYCH-UA 997 | E48: Independent Research in Psychology | F48: 4 | G48: Semester | H48: No credit | I48: TFRGEN NOCRDT | J48: 0 | K48: TX | L48: NC-RESEARCH | N48: Credit Evaluation Office | O48: Psychology | P48: 2024-10-05 | Q48: 2024-25 | R48: Yes | S48: train
A49: D-0048 | B49: NEU|COOP 3945 | C49: NEU | D49: COOP 3945 | E49: Co-op Work Experience | F49: 4 | G49: Semester | H49: No credit | I49: TFRGEN NOCRDT | J49: 0 | K49: TX | L49: NC-INTERNSHIP | N49: Credit Evaluation Office | O49: Career | P49: 2024-01-02 | Q49: 2023-24 | R49: Yes | S49: train
A50: D-0049 | B50: NEU|ECON 2350 | C50: NEU | D50: ECON 2350 | E50: Statistics for Economists | F50: 4 | G50: Semester | H50: Equivalent | I50: CAS EC 203 | J50: 4 | K50: T | L50: EQ-CONTENT | M50: 88 | N50: Evaluator EC-B | O50: Economics | P50: 2025-03-01 | Q50: 2023-24 | R50: Yes | S50: train
A51: D-0050 | B51: NEU|PSYC 3458 | C51: NEU | D51: PSYC 3458 | E51: Biological Psychology | F51: 4 | G51: Semester | H51: Equivalent | I51: CAS PS 231 | J51: 4 | K51: T | L51: EQ-CONTENT | M51: 100 | N51: Evaluator PS-B | O51: Psychology | P51: 2024-08-13 | Q51: 2024-25 | R51: Yes | S51: train
A52: D-0051 | B52: NEU|PSYC 3703 | C52: NEU | D52: PSYC 3703 | E52: Cognitive Neuroscience | F52: 4 | G52: Semester | H52: Equivalent | I52: CAS PS 320 | J52: 4 | K52: T | L52: EQ-CONTENT | M52: 88 | N52: Evaluator PS-A | O52: Psychology | P52: 2025-03-10 | Q52: 2024-25 | R52: Yes | S52: train
A53: D-0052 | B53: NEU|CS 2706 | C53: NEU | D53: CS 2706 | E53: Agile Methods and Entity-relationship Design | F53: 4 | G53: Semester | H53: Elective | I53: CAS CS 2TR | J53: 4 | K53: T | L53: EL-LOWOVERLAP | M53: 25 | N53: Evaluator CS-B | O53: Computer Science | P53: 2024-06-08 | Q53: 2023-24 | R53: Yes | S53: train
A54: D-0053 | B54: NYU|BIOL-UA 366 | C54: NYU | D54: BIOL-UA 366 | E54: Virology | F54: 4 | G54: Semester | H54: Equivalent | I54: CAS BI 380 | J54: 4 | K54: T | L54: EQ-EVALUATOR | M54: 75 | N54: Evaluator BI-B | O54: Biology | P54: 2024-11-25 | Q54: 2023-24 | R54: Yes | S54: train
A55: D-0054 | B55: NYU|PSYCH-UA 22 | C55: NYU | D55: PSYCH-UA 22 | E55: Perception | F55: 4 | G55: Semester | H55: Equivalent | I55: CAS PS 222 | J55: 4 | K55: T | L55: EQ-CONTENT | M55: 88 | N55: Evaluator PS-A | O55: Psychology | P55: 2024-02-01 | Q55: 2024-25 | R55: Yes | S55: train
A56: D-0055 | B56: NYU|PSYCH-UA 29 | C56: NYU | D56: PSYCH-UA 29 | E56: Cognition | F56: 4 | G56: Semester | H56: Equivalent | I56: CAS PS 336 | J56: 4 | K56: T | L56: EQ-CONTENT | M56: 100 | N56: Evaluator PS-B | O56: Psychology | P56: 2024-01-16 | Q56: 2023-24 | R56: Yes | S56: train
A57: D-0056 | B57: NEU|ECON 3712 | C57: NEU | D57: ECON 3712 | E57: IS-LM Model and Patents | F57: 4 | G57: Semester | H57: Elective | I57: CAS EC 2TR | J57: 4 | K57: T | L57: EL-LOWOVERLAP | M57: 38 | N57: Evaluator EC-A | O57: Economics | P57: 2024-06-23 | Q57: 2023-24 | R57: Yes | S57: train
A58: D-0057 | B58: NYU|CHEM-UA 125 | C58: NYU | D58: CHEM-UA 125 | E58: General Chemistry I | F58: 5 | G58: Semester | H58: Equivalent | I58: CAS CH 101 | J58: 5 | K58: T | L58: EQ-CONTENT | M58: 100 | N58: Evaluator BI-B | O58: Biology | P58: 2024-01-04 | Q58: 2024-25 | R58: Yes | S58: train
A59: D-0058 | B59: NEU|PSYC 3715 | C59: NEU | D59: PSYC 3715 | E59: Introduction to Cognitive Psychology | F59: 4 | G59: Semester | H59: Equivalent | I59: CAS PS 336 | J59: 4 | K59: T | L59: EQ-CONTENT | M59: 88 | N59: Evaluator PS-A | O59: Psychology | P59: 2025-02-25 | Q59: 2024-25 | R59: Yes | S59: train
A60: D-0059 | B60: NYU|CHEM-UA 363 | C60: NYU | D60: CHEM-UA 363 | E60: Physical Chemistry for Life Sciences | F60: 4 | G60: Semester | H60: Elective | I60: CAS CH 2TR | J60: 4 | K60: T | L60: EL-PARTIAL | M60: 62 | N60: Evaluator BI-A | O60: Biology | P60: 2024-05-24 | Q60: 2024-25 | R60: Yes | S60: train
A61: D-0060 | B61: NYU|BIOL-UA 166 | C61: NYU | D61: BIOL-UA 166 | E61: Ecology | F61: 4 | G61: Semester | H61: Equivalent | I61: CAS BI 225 | J61: 4 | K61: T | L61: EQ-CONTENT | M61: 88 | N61: Evaluator BI-B | O61: Biology | P61: 2024-05-12 | Q61: 2023-24 | R61: Yes | S61: train
... A101: D-0100 | B101: NEU|ECON 2706 | C101: NEU | D101: ECON 2706 | E101: Labor Economics | F101: 4 | G101: Semester | H101: Equivalent | I101: CAS EC 240 | J101: 4 | K101: T | L101: EQ-CONTENT | M101: 100 | N101: Evaluator EC-A | O101: Economics | P101: 2024-10-11 | Q101: 2023-24 | R101: No | S101: holdout

Sheet Syllabi Index
A1: File | B1: Ext ID | C1: Course | D1: School | E1: State | F1: Used by | G1: Expected match (gt) | H1: True overlap % (gt) | I1: Note
A2: syllabi/Syllabus_NYU_PSYCH-UA-10.pdf | B2: NYU|PSYCH-UA 10 | C2: PSYCH-UA 10 Statistics for the Behavioral Sciences | D2: New York University | E2: complete | F2: Maya Delgado | G2: CAS PS 211 | H2: 75 | I2: Maybe 1: on file at upload (~75% overlap with CAS PS 211; workbook: partial, statistics vs experimental design)
A3: syllabi/Syllabus_NYU_PSYCH-UA-25.pdf | B3: NYU|PSYCH-UA 25 | C3: PSYCH-UA 25 Cognitive Neuroscience | D3: New York University | E3: complete-late | F3: Maya Delgado | G3: CAS PS 231 | H3: 62 | I3: Maybe 2: missing at upload (TS); upload in demo step 7 (~62% overlap with CAS PS 231)
A4: syllabi/Syllabus_NEU_CS-2100.pdf | B4: NEU|CS 2100 | C4: CS 2100 Program Design and Implementation 1 | D4: Northeastern University | E4: complete | F4: Jordan Reyes | G4: CAS CS 112 | H4: 62 | I4: Partial (~62%) with CAS CS 112; workbook notes NU splits CS 112 across CS 2100 + CS 2700
A5: syllabi/Syllabus_NEU_CS-2700.pdf | B5: NEU|CS 2700 | C5: CS 2700 Data Structures and Analysis | D5: Northeastern University | E5: incomplete | F5: Jordan Reyes | G5: CAS CS 112 | H5: 75 | I5: INCOMPLETE: no learning outcomes or weekly schedule -> TM request
A6: syllabi/Syllabus_NEU_CHEM-1161.pdf | B6: NEU|CHEM 1161 | C6: CHEM 1161 General Chemistry for Science Majors | D6: Northeastern University | E6: complete | F6: Aisha Bello | G6: CAS CH 101 | H6: 62 | I6: NU one-semester general chemistry (~62% with CAS CH 101; may map to CH 101 or CH 102)
A7: syllabi/Syllabus_NEU_BIOL-2301.pdf | B7: NEU|BIOL 2301 | C7: BIOL 2301 Genetics and Molecular Biology | D7: Northeastern University | E7: complete | F7: Aisha Bello | G7: CAS BI 206 | H7: 75 | I7: Partial (~75%) with CAS BI 206 (genetics + molecular biology)
A8: syllabi/Syllabus_NEU_BIOL-3611.pdf | B8: NEU|BIOL 3611 | C8: BIOL 3611 Biochemistry | D8: Northeastern University | E8: complete | F8: Aisha Bello | G8: CAS CH 373 | H8: 87 | I8: High overlap (~88%) with CAS CH 373 Biochemistry 1 -> propose equivalent
A9: syllabi/Syllabus_NEU_BIOL-2299.pdf | B9: NEU|BIOL 2299 | C9: BIOL 2299 Inquiries in Biological Sciences | D9: Northeastern University | E9: complete | F9: Aisha Bello | G9: CAS BI 107 | H9: 37 | I9: Low overlap (~38%) with CAS BI 107 -> elective expected
A10: syllabi/Syllabus_NYU_ECON-UA-266.pdf | B10: NYU|ECON-UA 266 | C10: ECON-UA 266 Intro to Econometrics | D10: New York University | E10: complete-injection | F10: Liam Novak | G10: CAS EC 204 | H10: 62 | I10: RED-TEAM: contains a prompt-injection line; AI must ignore it (~62% with CAS EC 204)
A11: syllabi/Syllabus_NYU_PSYCH-UA-34.pdf | B11: NYU|PSYCH-UA 34 | C11: PSYCH-UA 34 Developmental Psychology | D11: New York University | E11: complete | F11: Evaluation set | G11: CAS PS 241 | H11: 87 | I11: Held-out course (~87% overlap with CAS PS 241)
A12: syllabi/Syllabus_NEU_BIOL-3712.pdf | B12: NEU|BIOL 3712 | C12: BIOL 3712 Molecular Biology | D12: Northeastern University | E12: complete | F12: Evaluation set | G12: CAS BI 350 | H12: 100 | I12: Held-out course (~100% overlap with CAS BI 350)
A13: syllabi/Syllabus_NEU_ECON-2706.pdf | B13: NEU|ECON 2706 | C13: ECON 2706 Labor Economics | D13: Northeastern University | E13: complete | F13: Evaluation set | G13: CAS EC 240 | H13: 100 | I13: Held-out course (~100% overlap with CAS EC 240)

Sheet Transcripts Index
A1: File | B1: Student ID | C1: Student | D1: School | E1: Course lines
A2: transcripts/Transcript_SYN-24001_NYU_Maya_Delgado.pdf | B2: SYN-24001 | C2: Maya R. Delgado | D2: New York University | E2: 5
A3: transcripts/Transcript_SYN-24001_PSC_Maya_Delgado.pdf | B3: SYN-24001 | C3: Maya R. Delgado | D3: Pinecrest State College (fictional) | E3: 1
A4: transcripts/Transcript_SYN-24002_NEU_Jordan_Reyes.pdf | B4: SYN-24002 | C4: Jordan A. Reyes | D4: Northeastern University | E4: 14
A5: transcripts/Transcript_SYN-24003_NEU_Aisha_Bello.pdf | B5: SYN-24003 | C5: Aisha K. Bello | D5: Northeastern University | E5: 12
A6: transcripts/Transcript_SYN-24004_NEU_Liam_Novak.pdf | B6: SYN-24004 | C6: Liam O. Novak | D6: Northeastern University | E6: 8
A7: transcripts/Transcript_SYN-24004_NYU_Liam_Novak.pdf | B7: SYN-24004 | C7: Liam O. Novak | D7: New York University | E7: 14
A8: transcripts/Transcript_SYN-24004_SOI_Liam_Novak.pdf | B8: SYN-24004 | C8: Liam O. Novak | D8: Summit Online Institute (fictional) | E8: 2

Sheet Rules
A1: Rule ID | B1: Category | C1: Rule | D1: Condition | E1: Outcome | F1: Reason code | G1: Source
A2: R01 | B2: Accreditation | C2: Only courses from regionally accredited institutions are eligible. | D2: school.accreditation | E2: No credit, TFRGEN NOCRDT, 0 units, TX | F2: NC-ACCRED | G2: Sponsor Q8
A3: R02 | B3: Course type | C3: Remedial/developmental, vocational, physical education and ROTC courses are ineligible. | D3: course.course_type | E3: No credit, TX | F3: NC-REMEDIAL / NC-VOC / NC-PE / NC-ROTC | G3: Sponsor Q8
A4: R03 | B4: Course type | C4: Internships, research and military or life experience are ineligible. | D4: course.course_type | E4: No credit, TX | F4: NC-INTERNSHIP / NC-RESEARCH | G4: Sponsor Q8
A5: R04 | B5: Credits | C5: One-credit courses are generally not accepted. | D5: credits = 1 | E5: No credit, TX | F5: NC-ONECREDIT | G5: Sponsor Q8
A6: R05 | B6: Grades | C6: Pass/Fail grades are generally not accepted. | D6: grade in (P, NP, S, U) | E6: No credit, TX | F6: NC-PASSFAIL | G6: Sponsor Q8
A7: R06 | B7: Grades | C7: Minimum grade C; C- and below are ineligible. External grades do not enter the BU GPA. | D7: min_grade = C | E7: No credit, TX | F7: NC-GRADE | G7: Brief; sponsor Q18
A8: R07 | B8: Age | C8: Courses five or more years old need review before any credit. | D8: term_year <= start_year - 5 | E8: Pending: age review | F8: RV-AGE | G8: Sponsor Q8
A9: R08 | B9: Conversion | C9: Quarter credits x 2/3, rounded to 2 decimals, course by course. | D9: calendar = Quarter | E9: units = ROUND(credits*2/3, 2) | F9: - | G9: Sponsor Q18/Q27
A10: R09 | B10: Units | C10: Units posted are always the units the student took (converted), never the BU course's credits. | D10: - | E10: - | F10: - | G10: Sponsor Q27
A11: R10 | B11: Existing match | C11: Check the equivalency table first; a reusable decision is applied without a syllabus. | D11: reusable = Yes | E11: Matched: BU course or TR elective, grade T | F11: (decision's code) | G11: Sponsor Q1, Q23
A12: R11 | B12: Conflicts | C12: Conflicting past decisions: the newest decision for the same catalog years wins; flag the conflict for the department. | D12: multiple decisions | E12: Apply newest; flag | F12: - | G12: Sponsor Q18
... A25: R24 | B25: Codes | C25: Equivalent -> specific BU course; elective -> BU code ending in TR; no credit -> TFRGEN NOCRDT, 0 units, TX. Every evaluated course shows grade T (TX for no credit). | D25: - | E25: - | F25: - | G25: Sponsor Q24/Q27

Sheet Reason Codes
A1: Reason code | B1: Decision | C1: Meaning
A2: EQ-CONTENT | B2: Equivalent | C2: Substantially equivalent content and level (>=80% overlap)
A3: EQ-EVALUATOR | B3: Equivalent | C3: Partial overlap; evaluator judged it equivalent
A4: EL-PARTIAL | B4: Elective | C4: Partial overlap; evaluator judged elective
A5: EL-LOWOVERLAP | B5: Elective | C5: Below 50% overlap; eligible course -> elective
A6: EL-NOEQUIV | B6: Elective | C6: Eligible course with no BU equivalent
A7: EL-DUPLICATE | B7: Elective | C7: Second course covering the same BU course
A8: EL-RESIDENCY | B8: Elective | C8: Requirement must be taken at BU; units post as elective
A9: NC-GRADE | B9: No credit | C9: Grade below C
A10: NC-PASSFAIL | B10: No credit | C10: Pass/Fail grade
A11: NC-ONECREDIT | B11: No credit | C11: One-credit course
A12: NC-REMEDIAL | B12: No credit | C12: Remedial / developmental course
... A23: CAP-68 | B23: Flag | C23: 68-unit external cap reached

Sheet Test Cases
A1: Test ID | B1: Type | C1: Input | D1: Expected
A2: T01 | B2: Sponsor example | C2: 3-credit semester film course, grade B, no BU equivalent | D2: Elective, 3.00 units, grade T
A3: T02 | B3: Sponsor example | C3: Maya: PSC PSY 215, 4 quarter credits, grade B, no equivalent | D3: Elective CAS PS 2TR, 2.67 units (4 x 2/3), grade T
A4: T03 | B4: Sponsor example | C4: Jordan: NU MATH 1341 with grade C- | D4: No credit, 0 units, TFRGEN NOCRDT, TX
A5: T04 | B5: Sponsor example | C5: Jordan: NU MATH 0990 developmental math, grade A | D5: No credit, 0 units, TFRGEN NOCRDT, TX
A6: T05 | B6: Lab credits | C6: Aisha: NU 5-credit lab courses (BIOL 1107) | D6: 5.00 units (student's units, not BU's 4)
A7: T06 | B7: Duplicate | C7: Jordan: NU CS 1990 after CS 2000 (both CAS CS 111) | D7: Second course -> CAS CS 1TR elective, EL-DUPLICATE
A8: T07 | B8: Residency | C8: Jordan: NU CS 4400 maps to CAS CS 320 (Group C) | D8: Elective CAS CS 2TR, 4 units, EL-RESIDENCY
A9: T08 | B9: Pass/Fail | C9: Jordan: NU FILM 1101 graded P | D9: No credit, NC-PASSFAIL
A10: T09 | B10: Age | C10: Jordan: NU HIST 1130 from Fall 2019, BU start Fall 2026 | D10: Pending age review, RV-AGE
A11: T10 | B11: Accreditation | C11: Liam: two Summit Online Institute courses (fictional, not regionally accredited) | D11: No credit, NC-ACCRED
A12: T11 | B12: 68-unit cap | C12: Liam: total countable units exceed 68 | D12: Units beyond 68 do not count; CAP-68 flag on the courses that cross it
... A21: T20 | B21: Combined course | C21: Aisha: NU CHEM 1161 one-semester general chemistry | D21: Evaluator decides CH 101 vs CH 102 (workbook note)
